Workbook

Sheet Start Here
A1: HUNGRY ARTISAN - SHIPMENT LOGISTICS COMPARISON
A2: From Scratch. On Purpose. | DRAFT for the 2027 logistics plan | Owner: Victoria | Compares total cost to ship, not product profitability
A4: HOW TO USE (per shipment)
A5: 1. Products | B5: Keep the Products tab current: carton size, kg, unit COGS, HTS and duty rates.
A6: 2. Shipment Setup | B6: Pick one or more products, enter units and how many go to AWD, FBA direct, Walmart WFS and TikTok FBT. Choose whether shared costs split by CBM or weight, and whether to include cost of capital.
A7: 3. Amazon Path (AGL) | B7: Enter the AGL quote for this shipment. Duty and tariff are always paid separately; AWD fees come from Products and Rate Card.
A8: 4. Scenario 1, 2, 3 | B8: Enter up to three third-party quotes with identical inputs. Pick the Incoterm (EXW, FOB or DDP) and mode (FCL, LCL or Air). Greyed rows do not apply. DDP skips tariff.
A9: 5. Comparison | B9: Read the total landed cost, cost per unit, difference vs the Amazon path, cost by destination and by product, plus cheapest and fastest flags.
A10: 6. Checks and Log | B10: Clear every CHECK on the Checks tab, then record the decision on the Shipment Log.
A12: COLOR KEY
A13: Yellow, blue text | B13: Input - type here
A14: Cream | B14: Calculated - do not overwrite
A15: Grey | B15: Does not apply to the chosen Incoterm / mode
A17: ASSUMPTIONS
A18: Duty is calculated on customs value (unit COGS x units).
A19: Shared costs (freight, origin, destination, hub, other) are split by CBM or weight; delivery costs go to their own destination.
A20: The AGL discount is already inside the AGL quote. The placement-fee waiver on AWD appears as $0 placement fee plus a memo.
A21: Transparency labels and other costs identical on every path are left out.
A22: Seeded AWD rates are Sept 2026 figures: VERIFY before use.

Sheet Shipment Setup
A1: SHIPMENT SETUP
A2: Enter the shipment once. Every path (Amazon AGL and Scenarios 1-3) is costed from this tab. Yellow = input.
A4: SHIPMENT
A5: Shipment name / PO
A6: Date
A7: Allocate shared costs by | B7: CBM | C7: Mixed loads: splits freight between products by CBM or by weight
A8: Include cost of capital? | B8: No
A9: Annual cost of capital % | B9: 0.1
A10: Origin port / factory
A12: PRODUCTS IN THIS SHIPMENT (1 to 10 rows) - pick the product, enter units and where the units go
A13: Product | B13: Units | C13: Units / carton | D13: Cartons | E13: CBM / carton | F13: Total CBM | G13: kg / carton | H13: Total kg | I13: Unit COGS | J13: Customs value | K13: HTS | L13: Duty % | M13: Tariff % | N13: Other % | O13: Duty + tariff $ | P13: To AWD (units) | Q13: To FBA direct (units) | R13: To Walmart WFS (units) | S13: To TikTok FBT (units) | T13: Unallocated units | U13: CBM / unit | V13: kg / unit | W13: Duty $ / unit | X13: Alloc. weight / unit | Y13: Share of shared cost | Z13: AWD proc. $/unit | AA13: AWD to FBA $/unit
A14: Classic Food Mill | B14: 1000 | C14: =IFERROR(VLOOKUP($A14,Products!$A$5:$O$34,3,FALSE),0) | D14: =IF(AND(N($B14)>0,N($C14)>0),ROUNDUP($B14/$C14,0),0) -> 0 | E14: =IFERROR(VLOOKUP($A14,Products!$A$5:$O$34,8,FALSE),0) -> 0 | F14: =D14*E14 -> 0 | G14: =IFERROR(VLOOKUP($A14,Products!$A$5:$O$34,7,FALSE),0) | H14: =D14*G14 -> 0 | I14: =IFERROR(VLOOKUP($A14,Products!$A$5:$O$34,9,FALSE),0) | J14: =N(B14)*I14 -> 0 | K14: =IFERROR(VLOOKUP($A14,Products!$A$5:$O$34,10,FALSE)&"","") | L14: =IFERROR(VLOOKUP($A14,Products!$A$5:$O$34,11,FALSE),0) | M14: =IFERROR(VLOOKUP($A14,Products!$A$5:$O$34,12,FALSE),0) | N14: =IFERROR(VLOOKUP($A14,Products!$A$5:$O$34,13,FALSE),0) | O14: =J14*(L14+M14+N14) -> 0 | P14: 500 | Q14: 250 | R14: 100 | S14: 150 | T14: =N(B14)-SUM(P14:S14) -> 0 | U14: =IF(N(B14)>0,F14/B14,0) -> 0 | V14: =IF(N(B14)>0,H14/B14,0) -> 0 | W14: =IF(N(B14)>0,O14/B14,0) -> 0 | X14: =IF($B$7="Weight",V14,U14) -> 0 | Y14: =IF(SUMPRODUCT($B$14:$B$23,$X$14:$X$23)=0,0,N(B14)*X14/SUMPRODUCT($B$14:$B$23,$X$14:$X$23)) -> 0 | Z14: =IFERROR(VLOOKUP($A14,Products!$A$5:$O$34,14,FALSE),0) -> 0.23 | AA14: =IFERROR(VLOOKUP($A14,Products!$A$5:$O$34,15,FALSE),0) -> 0.4
C15: =IFERROR(VLOOKUP($A15,Products!$A$5:$O$34,3,FALSE),0) -> 0 | D15: =IF(AND(N($B15)>0,N($C15)>0),ROUNDUP($B15/$C15,0),0) -> 0 | E15: =IFERROR(VLOOKUP($A15,Products!$A$5:$O$34,8,FALSE),0) -> 0 | F15: =D15*E15 -> 0 | G15: =IFERROR(VLOOKUP($A15,Products!$A$5:$O$34,7,FALSE),0) -> 0 | H15: =D15*G15 -> 0 | I15: =IFERROR(VLOOKUP($A15,Products!$A$5:$O$34,9,FALSE),0) -> 0 | J15: =N(B15)*I15 -> 0 | K15: =IFERROR(VLOOKUP($A15,Products!$A$5:$O$34,10,FALSE)&"","") | L15: =IFERROR(VLOOKUP($A15,Products!$A$5:$O$34,11,FALSE),0) -> 0 | M15: =IFERROR(VLOOKUP($A15,Products!$A$5:$O$34,12,FALSE),0) -> 0 | N15: =IFERROR(VLOOKUP($A15,Products!$A$5:$O$34,13,FALSE),0) -> 0 | O15: =J15*(L15+M15+N15) -> 0 | T15: =N(B15)-SUM(P15:S15) -> 0 | U15: =IF(N(B15)>0,F15/B15,0) -> 0 | V15: =IF(N(B15)>0,H15/B15,0) -> 0 | W15: =IF(N(B15)>0,O15/B15,0) -> 0 | X15: =IF($B$7="Weight",V15,U15) -> 0 | Y15: =IF(SUMPRODUCT($B$14:$B$23,$X$14:$X$23)=0,0,N(B15)*X15/SUMPRODUCT($B$14:$B$23,$X$14:$X$23)) -> 0 | Z15: =IFERROR(VLOOKUP($A15,Products!$A$5:$O$34,14,FALSE),0) -> 0 | AA15: =IFERROR(VLOOKUP($A15,Products!$A$5:$O$34,15,FALSE),0) -> 0
C16: =IFERROR(VLOOKUP($A16,Products!$A$5:$O$34,3,FALSE),0) -> 0 | D16: =IF(AND(N($B16)>0,N($C16)>0),ROUNDUP($B16/$C16,0),0) -> 0 | E16: =IFERROR(VLOOKUP($A16,Products!$A$5:$O$34,8,FALSE),0) -> 0 | F16: =D16*E16 -> 0 | G16: =IFERROR(VLOOKUP($A16,Products!$A$5:$O$34,7,FALSE),0) -> 0 | H16: =D16*G16 -> 0 | I16: =IFERROR(VLOOKUP($A16,Products!$A$5:$O$34,9,FALSE),0) -> 0 | J16: =N(B16)*I16 -> 0 | K16: =IFERROR(VLOOKUP($A16,Products!$A$5:$O$34,10,FALSE)&"","") | L16: =IFERROR(VLOOKUP($A16,Products!$A$5:$O$34,11,FALSE),0) -> 0 | M16: =IFERROR(VLOOKUP($A16,Products!$A$5:$O$34,12,FALSE),0) -> 0 | N16: =IFERROR(VLOOKUP($A16,Products!$A$5:$O$34,13,FALSE),0) -> 0 | O16: =J16*(L16+M16+N16) -> 0 | T16: =N(B16)-SUM(P16:S16) -> 0 | U16: =IF(N(B16)>0,F16/B16,0) -> 0 | V16: =IF(N(B16)>0,H16/B16,0) -> 0 | W16: =IF(N(B16)>0,O16/B16,0) -> 0 | X16: =IF($B$7="Weight",V16,U16) -> 0 | Y16: =IF(SUMPRODUCT($B$14:$B$23,$X$14:$X$23)=0,0,N(B16)*X16/SUMPRODUCT($B$14:$B$23,$X$14:$X$23)) -> 0 | Z16: =IFERROR(VLOOKUP($A16,Products!$A$5:$O$34,14,FALSE),0) -> 0 | AA16: =IFERROR(VLOOKUP($A16,Products!$A$5:$O$34,15,FALSE),0) -> 0
C17: =IFERROR(VLOOKUP($A17,Products!$A$5:$O$34,3,FALSE),0) -> 0 | D17: =IF(AND(N($B17)>0,N($C17)>0),ROUNDUP($B17/$C17,0),0) -> 0 | E17: =IFERROR(VLOOKUP($A17,Products!$A$5:$O$34,8,FALSE),0) -> 0 | F17: =D17*E17 -> 0 | G17: =IFERROR(VLOOKUP($A17,Products!$A$5:$O$34,7,FALSE),0) -> 0 | H17: =D17*G17 -> 0 | I17: =IFERROR(VLOOKUP($A17,Products!$A$5:$O$34,9,FALSE),0) -> 0 | J17: =N(B17)*I17 -> 0 | K17: =IFERROR(VLOOKUP($A17,Products!$A$5:$O$34,10,FALSE)&"","") | L17: =IFERROR(VLOOKUP($A17,Products!$A$5:$O$34,11,FALSE),0) -> 0 | M17: =IFERROR(VLOOKUP($A17,Products!$A$5:$O$34,12,FALSE),0) -> 0 | N17: =IFERROR(VLOOKUP($A17,Products!$A$5:$O$34,13,FALSE),0) -> 0 | O17: =J17*(L17+M17+N17) -> 0 | T17: =N(B17)-SUM(P17:S17) -> 0 | U17: =IF(N(B17)>0,F17/B17,0) -> 0 | V17: =IF(N(B17)>0,H17/B17,0) -> 0 | W17: =IF(N(B17)>0,O17/B17,0) -> 0 | X17: =IF($B$7="Weight",V17,U17) -> 0 | Y17: =IF(SUMPRODUCT($B$14:$B$23,$X$14:$X$23)=0,0,N(B17)*X17/SUMPRODUCT($B$14:$B$23,$X$14:$X$23)) -> 0 | Z17: =IFERROR(VLOOKUP($A17,Products!$A$5:$O$34,14,FALSE),0) -> 0 | AA17: =IFERROR(VLOOKUP($A17,Products!$A$5:$O$34,15,FALSE),0) -> 0
C18: =IFERROR(VLOOKUP($A18,Products!$A$5:$O$34,3,FALSE),0) -> 0 | D18: =IF(AND(N($B18)>0,N($C18)>0),ROUNDUP($B18/$C18,0),0) -> 0 | E18: =IFERROR(VLOOKUP($A18,Products!$A$5:$O$34,8,FALSE),0) -> 0 | F18: =D18*E18 -> 0 | G18: =IFERROR(VLOOKUP($A18,Products!$A$5:$O$34,7,FALSE),0) -> 0 | H18: =D18*G18 -> 0 | I18: =IFERROR(VLOOKUP($A18,Products!$A$5:$O$34,9,FALSE),0) -> 0 | J18: =N(B18)*I18 -> 0 | K18: =IFERROR(VLOOKUP($A18,Products!$A$5:$O$34,10,FALSE)&"","") | L18: =IFERROR(VLOOKUP($A18,Products!$A$5:$O$34,11,FALSE),0) -> 0 | M18: =IFERROR(VLOOKUP($A18,Products!$A$5:$O$34,12,FALSE),0) -> 0 | N18: =IFERROR(VLOOKUP($A18,Products!$A$5:$O$34,13,FALSE),0) -> 0 | O18: =J18*(L18+M18+N18) -> 0 | T18: =N(B18)-SUM(P18:S18) -> 0 | U18: =IF(N(B18)>0,F18/B18,0) -> 0 | V18: =IF(N(B18)>0,H18/B18,0) -> 0 | W18: =IF(N(B18)>0,O18/B18,0) -> 0 | X18: =IF($B$7="Weight",V18,U18) -> 0 | Y18: =IF(SUMPRODUCT($B$14:$B$23,$X$14:$X$23)=0,0,N(B18)*X18/SUMPRODUCT($B$14:$B$23,$X$14:$X$23)) -> 0 | Z18: =IFERROR(VLOOKUP($A18,Products!$A$5:$O$34,14,FALSE),0) -> 0 | AA18: =IFERROR(VLOOKUP($A18,Products!$A$5:$O$34,15,FALSE),0) -> 0
C19: =IFERROR(VLOOKUP($A19,Products!$A$5:$O$34,3,FALSE),0) -> 0 | D19: =IF(AND(N($B19)>0,N($C19)>0),ROUNDUP($B19/$C19,0),0) -> 0 | E19: =IFERROR(VLOOKUP($A19,Products!$A$5:$O$34,8,FALSE),0) -> 0 | F19: =D19*E19 -> 0 | G19: =IFERROR(VLOOKUP($A19,Products!$A$5:$O$34,7,FALSE),0) -> 0 | H19: =D19*G19 -> 0 | I19: =IFERROR(VLOOKUP($A19,Products!$A$5:$O$34,9,FALSE),0) -> 0 | J19: =N(B19)*I19 -> 0 | K19: =IFERROR(VLOOKUP($A19,Products!$A$5:$O$34,10,FALSE)&"","") | L19: =IFERROR(VLOOKUP($A19,Products!$A$5:$O$34,11,FALSE),0) -> 0 | M19: =IFERROR(VLOOKUP($A19,Products!$A$5:$O$34,12,FALSE),0) -> 0 | N19: =IFERROR(VLOOKUP($A19,Products!$A$5:$O$34,13,FALSE),0) -> 0 | O19: =J19*(L19+M19+N19) -> 0 | T19: =N(B19)-SUM(P19:S19) -> 0 | U19: =IF(N(B19)>0,F19/B19,0) -> 0 | V19: =IF(N(B19)>0,H19/B19,0) -> 0 | W19: =IF(N(B19)>0,O19/B19,0) -> 0 | X19: =IF($B$7="Weight",V19,U19) -> 0 | Y19: =IF(SUMPRODUCT($B$14:$B$23,$X$14:$X$23)=0,0,N(B19)*X19/SUMPRODUCT($B$14:$B$23,$X$14:$X$23)) -> 0 | Z19: =IFERROR(VLOOKUP($A19,Products!$A$5:$O$34,14,FALSE),0) -> 0 | AA19: =IFERROR(VLOOKUP($A19,Products!$A$5:$O$34,15,FALSE),0) -> 0
C20: =IFERROR(VLOOKUP($A20,Products!$A$5:$O$34,3,FALSE),0) -> 0 | D20: =IF(AND(N($B20)>0,N($C20)>0),ROUNDUP($B20/$C20,0),0) -> 0 | E20: =IFERROR(VLOOKUP($A20,Products!$A$5:$O$34,8,FALSE),0) -> 0 | F20: =D20*E20 -> 0 | G20: =IFERROR(VLOOKUP($A20,Products!$A$5:$O$34,7,FALSE),0) -> 0 | H20: =D20*G20 -> 0 | I20: =IFERROR(VLOOKUP($A20,Products!$A$5:$O$34,9,FALSE),0) -> 0 | J20: =N(B20)*I20 -> 0 | K20: =IFERROR(VLOOKUP($A20,Products!$A$5:$O$34,10,FALSE)&"","") | L20: =IFERROR(VLOOKUP($A20,Products!$A$5:$O$34,11,FALSE),0) -> 0 | M20: =IFERROR(VLOOKUP($A20,Products!$A$5:$O$34,12,FALSE),0) -> 0 | N20: =IFERROR(VLOOKUP($A20,Products!$A$5:$O$34,13,FALSE),0) -> 0 | O20: =J20*(L20+M20+N20) -> 0 | T20: =N(B20)-SUM(P20:S20) -> 0 | U20: =IF(N(B20)>0,F20/B20,0) -> 0 | V20: =IF(N(B20)>0,H20/B20,0) -> 0 | W20: =IF(N(B20)>0,O20/B20,0) -> 0 | X20: =IF($B$7="Weight",V20,U20) -> 0 | Y20: =IF(SUMPRODUCT($B$14:$B$23,$X$14:$X$23)=0,0,N(B20)*X20/SUMPRODUCT($B$14:$B$23,$X$14:$X$23)) -> 0 | Z20: =IFERROR(VLOOKUP($A20,Products!$A$5:$O$34,14,FALSE),0) -> 0 | AA20: =IFERROR(VLOOKUP($A20,Products!$A$5:$O$34,15,FALSE),0) -> 0
C21: =IFERROR(VLOOKUP($A21,Products!$A$5:$O$34,3,FALSE),0) -> 0 | D21: =IF(AND(N($B21)>0,N($C21)>0),ROUNDUP($B21/$C21,0),0) -> 0 | E21: =IFERROR(VLOOKUP($A21,Products!$A$5:$O$34,8,FALSE),0) -> 0 | F21: =D21*E21 -> 0 | G21: =IFERROR(VLOOKUP($A21,Products!$A$5:$O$34,7,FALSE),0) -> 0 | H21: =D21*G21 -> 0 | I21: =IFERROR(VLOOKUP($A21,Products!$A$5:$O$34,9,FALSE),0) -> 0 | J21: =N(B21)*I21 -> 0 | K21: =IFERROR(VLOOKUP($A21,Products!$A$5:$O$34,10,FALSE)&"","") | L21: =IFERROR(VLOOKUP($A21,Products!$A$5:$O$34,11,FALSE),0) -> 0 | M21: =IFERROR(VLOOKUP($A21,Products!$A$5:$O$34,12,FALSE),0) -> 0 | N21: =IFERROR(VLOOKUP($A21,Products!$A$5:$O$34,13,FALSE),0) -> 0 | O21: =J21*(L21+M21+N21) -> 0 | T21: =N(B21)-SUM(P21:S21) -> 0 | U21: =IF(N(B21)>0,F21/B21,0) -> 0 | V21: =IF(N(B21)>0,H21/B21,0) -> 0 | W21: =IF(N(B21)>0,O21/B21,0) -> 0 | X21: =IF($B$7="Weight",V21,U21) -> 0 | Y21: =IF(SUMPRODUCT($B$14:$B$23,$X$14:$X$23)=0,0,N(B21)*X21/SUMPRODUCT($B$14:$B$23,$X$14:$X$23)) -> 0 | Z21: =IFERROR(VLOOKUP($A21,Products!$A$5:$O$34,14,FALSE),0) -> 0 | AA21: =IFERROR(VLOOKUP($A21,Products!$A$5:$O$34,15,FALSE),0) -> 0
C22: =IFERROR(VLOOKUP($A22,Products!$A$5:$O$34,3,FALSE),0) -> 0 | D22: =IF(AND(N($B22)>0,N($C22)>0),ROUNDUP($B22/$C22,0),0) -> 0 | E22: =IFERROR(VLOOKUP($A22,Products!$A$5:$O$34,8,FALSE),0) -> 0 | F22: =D22*E22 -> 0 | G22: =IFERROR(VLOOKUP($A22,Products!$A$5:$O$34,7,FALSE),0) -> 0 | H22: =D22*G22 -> 0 | I22: =IFERROR(VLOOKUP($A22,Products!$A$5:$O$34,9,FALSE),0) -> 0 | J22: =N(B22)*I22 -> 0 | K22: =IFERROR(VLOOKUP($A22,Products!$A$5:$O$34,10,FALSE)&"","") | L22: =IFERROR(VLOOKUP($A22,Products!$A$5:$O$34,11,FALSE),0) -> 0 | M22: =IFERROR(VLOOKUP($A22,Products!$A$5:$O$34,12,FALSE),0) -> 0 | N22: =IFERROR(VLOOKUP($A22,Products!$A$5:$O$34,13,FALSE),0) -> 0 | O22: =J22*(L22+M22+N22) -> 0 | T22: =N(B22)-SUM(P22:S22) -> 0 | U22: =IF(N(B22)>0,F22/B22,0) -> 0 | V22: =IF(N(B22)>0,H22/B22,0) -> 0 | W22: =IF(N(B22)>0,O22/B22,0) -> 0 | X22: =IF($B$7="Weight",V22,U22) -> 0 | Y22: =IF(SUMPRODUCT($B$14:$B$23,$X$14:$X$23)=0,0,N(B22)*X22/SUMPRODUCT($B$14:$B$23,$X$14:$X$23)) -> 0 | Z22: =IFERROR(VLOOKUP($A22,Products!$A$5:$O$34,14,FALSE),0) -> 0 | AA22: =IFERROR(VLOOKUP($A22,Products!$A$5:$O$34,15,FALSE),0) -> 0
C23: =IFERROR(VLOOKUP($A23,Products!$A$5:$O$34,3,FALSE),0) -> 0 | D23: =IF(AND(N($B23)>0,N($C23)>0),ROUNDUP($B23/$C23,0),0) -> 0 | E23: =IFERROR(VLOOKUP($A23,Products!$A$5:$O$34,8,FALSE),0) -> 0 | F23: =D23*E23 -> 0 | G23: =IFERROR(VLOOKUP($A23,Products!$A$5:$O$34,7,FALSE),0) -> 0 | H23: =D23*G23 -> 0 | I23: =IFERROR(VLOOKUP($A23,Products!$A$5:$O$34,9,FALSE),0) -> 0 | J23: =N(B23)*I23 -> 0 | K23: =IFERROR(VLOOKUP($A23,Products!$A$5:$O$34,10,FALSE)&"","") | L23: =IFERROR(VLOOKUP($A23,Products!$A$5:$O$34,11,FALSE),0) -> 0 | M23: =IFERROR(VLOOKUP($A23,Products!$A$5:$O$34,12,FALSE),0) -> 0 | N23: =IFERROR(VLOOKUP($A23,Products!$A$5:$O$34,13,FALSE),0) -> 0 | O23: =J23*(L23+M23+N23) -> 0 | T23: =N(B23)-SUM(P23:S23) -> 0 | U23: =IF(N(B23)>0,F23/B23,0) -> 0 | V23: =IF(N(B23)>0,H23/B23,0) -> 0 | W23: =IF(N(B23)>0,O23/B23,0) -> 0 | X23: =IF($B$7="Weight",V23,U23) -> 0 | Y23: =IF(SUMPRODUCT($B$14:$B$23,$X$14:$X$23)=0,0,N(B23)*X23/SUMPRODUCT($B$14:$B$23,$X$14:$X$23)) -> 0 | Z23: =IFERROR(VLOOKUP($A23,Products!$A$5:$O$34,14,FALSE),0) -> 0 | AA23: =IFERROR(VLOOKUP($A23,Products!$A$5:$O$34,15,FALSE),0) -> 0
A24: TOTAL | B24: =SUM(B14:B23) -> 1000 | D24: =SUM(D14:D23) -> 0 | F24: =SUM(F14:F23) -> 0 | H24: =SUM(H14:H23) -> 0 | J24: =SUM(J14:J23) -> 0 | O24: =SUM(O14:O23) -> 0 | P24: =SUM(P14:P23) -> 500 | Q24: =SUM(Q14:Q23) -> 250 | R24: =SUM(R14:R23) -> 100 | S24: =SUM(S14:S23) -> 150 | T24: =SUM(T14:T23) -> 0 | Y24: =SUM(Y14:Y23) -> 0
A25: Duty is calculated on customs value (unit COGS x units). Unallocated units must be 0. Columns U:AA are helper calculations.

Sheet Amazon Path (AGL)
A1: AMAZON PATH - CHINA > AGL > AWD > FBA / WFS / FBT
A2: Enter the AGL quote for this shipment. AWD fees come from Products and Rate Card. AGL never includes duty and tariff - they are always paid separately.
A4: 1. AGL QUOTE (per shipment) | E4: RESULTS (output only)
A5: AGL quote reference | E5: Main freight / all-in quote | F5: =B17 -> 0
A6: Quote valid until | E6: Origin charges | F6: =N(B18) -> 0
A7: Mode | C7: FCL, LCL or Air | E7: Destination port, brokerage, insurance | F7: =N(B20)+N(B21) -> 0
A8: Transit days (departure to AWD receipt) | E8: Duty & tariff | F8: =IF(B7="",0,B22) -> 0
A9: Days from AWD receipt to sellable stock | E9: Delivery to AWD | F9: =0 -> 0
A10: 2. AGL FREIGHT (AGL discount is already inside the quote) | E10: Delivery / transfer to FBA | F10: =IF(B7="",0,B25) -> 0
A11: FCL: number of containers | E11: Delivery / transfer to Walmart WFS | F11: =N(B28) -> 0
A12: FCL: price per container ($) | E12: Delivery / transfer to TikTok FBT | F12: =N(B29) -> 0
A13: LCL: rate per CBM ($) | E13: Inbound placement fees | F13: =0 -> 0 | G13: Placement fee waived: $0
A14: LCL: minimum charge ($) | E14: Hub storage, handling & AWD fees | F14: =IF(B7="",0,B24+B27) -> 0
A15: Air: rate per kg ($) | E15: Other fees | F15: =N(B30) -> 0
A16: Air: chargeable kg (calculated) | B16: =MAX('Shipment Setup'!H24,'Shipment Setup'!F24*'Rate Card'!B7) -> 0 | E16: TOTAL LANDED COST (shipment) | F16: =SUM(F5:F15) -> 0
A17: AGL freight total (calculated) | B17: =IF(B7="FCL",N(B11)*N(B12),IF(B7="LCL",MAX(N(B14),'Shipment Setup'!F24*N(B13)),IF(B7="Air",B16*N(B15),0))) -> 0 | E17: Cost per unit | F17: =IF(N('Shipment Setup'!B24)>0,F16/'Shipment Setup'!B24,0) -> 0
A18: Other AGL charges billed by AGL ($) | E18: Days: transit + to sellable | F18: =N(B8)+N(B9) -> 0
A19: 3. DUTY, TARIFF AND CUSTOMS (always paid separately) | E19: Cost of capital in transit (optional) | F19: =IF('Shipment Setup'!B8="Yes",F16*N('Shipment Setup'!B9)*F18/365,0) -> 0
A20: Customs brokerage, ISF, bond ($) | E20: Total incl. cost of capital | F20: =F16+F19 -> 0
A21: Cargo insurance ($) | E21: Cost per unit incl. capital | F21: =IF(N('Shipment Setup'!B24)>0,F20/'Shipment Setup'!B24,0) -> 0
A22: Duty & tariff (calculated from Shipment Setup) | B22: ='Shipment Setup'!O24 -> 0
A23: 4. AWD AND AMAZON FEES | E23: BY DESTINATION
A24: AWD inbound + processing (calculated) | B24: =SUMPRODUCT('Shipment Setup'!B14:B23,'Shipment Setup'!Z14:Z23) -> 230 | C24: All units x Products rate | E24: Destination | F24: Units | G24: Total cost | H24: Cost / unit | I24: Alloc. weight | J24: Direct cost
A25: AWD to FBA transfer (calculated) | B25: =SUMPRODUCT('Shipment Setup'!Q14:Q23,'Shipment Setup'!AA14:AA23) -> 100 | C25: FBA units x Products rate | E25: AWD | F25: ='Shipment Setup'!P24 -> 500 | G25: =IFERROR($F$43*I25/SUMPRODUCT('Shipment Setup'!B14:B23,'Shipment Setup'!X14:X23),0)+J25+(SUMPRODUCT('Shipment Setup'!P14:P23,'Shipment Setup'!W14:W23)) -> 0 | H25: =IF(F25>0,G25/F25,0) -> 0 | I25: =SUMPRODUCT('Shipment Setup'!P14:P23,'Shipment Setup'!X14:X23) -> 0 | J25: =F9 -> 0
A26: Average months stored in AWD | E26: FBA direct | F26: ='Shipment Setup'!Q24 -> 250 | G26: =IFERROR($F$43*I26/SUMPRODUCT('Shipment Setup'!B14:B23,'Shipment Setup'!X14:X23),0)+J26+(SUMPRODUCT('Shipment Setup'!Q14:Q23,'Shipment Setup'!W14:W23)) -> 0 | H26: =IF(F26>0,G26/F26,0) -> 0 | I26: =SUMPRODUCT('Shipment Setup'!Q14:Q23,'Shipment Setup'!X14:X23) -> 0 | J26: =F10+F13 -> 0
A27: AWD storage (calculated) | B27: ='Shipment Setup'!F24*N('Rate Card'!B6)*N(B26) -> 0 | C27: CBM x Rate Card $/CBM/month x months | E27: Walmart WFS | F27: ='Shipment Setup'!R24 -> 100 | G27: =IFERROR($F$43*I27/SUMPRODUCT('Shipment Setup'!B14:B23,'Shipment Setup'!X14:X23),0)+J27+(SUMPRODUCT('Shipment Setup'!R14:R23,'Shipment Setup'!W14:W23)) -> 0 | H27: =IF(F27>0,G27/F27,0) -> 0 | I27: =SUMPRODUCT('Shipment Setup'!R14:R23,'Shipment Setup'!X14:X23) -> 0 | J27: =F11 -> 0
A28: AWD to Walmart WFS transfer total ($) | E28: TikTok FBT | F28: ='Shipment Setup'!S24 -> 150 | G28: =IFERROR($F$43*I28/SUMPRODUCT('Shipment Setup'!B14:B23,'Shipment Setup'!X14:X23),0)+J28+(SUMPRODUCT('Shipment Setup'!S14:S23,'Shipment Setup'!W14:W23)) -> 0 | H28: =IF(F28>0,G28/F28,0) -> 0 | I28: =SUMPRODUCT('Shipment Setup'!S14:S23,'Shipment Setup'!X14:X23) -> 0 | J28: =F12 -> 0
A29: AWD to TikTok FBT transfer total ($)
A30: Other fees ($) | E30: BY PRODUCT
A31: 5. DISCOUNT MEMOS (not added to total) | E31: Product | F31: Units | G31: Total cost | H31: Cost / unit
A32: Placement fee waived by AWD (memo $) | B32: =N('Shipment Setup'!Q24)*N('Rate Card'!B5) -> 125 | C32: FBA units x Rate Card placement fee | E32: =IF('Shipment Setup'!A14="","",'Shipment Setup'!A14) -> Classic Food Mill | F32: =N('Shipment Setup'!B14) -> 1000 | G32: =IF(N('Shipment Setup'!B14)>0,$F$43*'Shipment Setup'!Y14+'Shipment Setup'!O14+IFERROR('Shipment Setup'!P14*'Shipment Setup'!X14/$I$25,0)*$J$25+IFERROR('Shipment Setup'!Q14*'Shipment Setup'!X14/$I$26,0)*$J$26+IFERROR('Shipment Setup'!R14*'Shipment Setup'!X14/$I$27,0)*$J$27+IFERROR('Shipment Setup'!S14*'Shipment Setup'!X14/$I$28,0)*$J$28,0) -> 0 | H32: =IF(F32>0,G32/F32,0) -> 0
A33: Optional: market freight quote for the same load ($) | E33: =IF('Shipment Setup'!A15="","",'Shipment Setup'!A15) | F33: =N('Shipment Setup'!B15) -> 0 | G33: =IF(N('Shipment Setup'!B15)>0,$F$43*'Shipment Setup'!Y15+'Shipment Setup'!O15+IFERROR('Shipment Setup'!P15*'Shipment Setup'!X15/$I$25,0)*$J$25+IFERROR('Shipment Setup'!Q15*'Shipment Setup'!X15/$I$26,0)*$J$26+IFERROR('Shipment Setup'!R15*'Shipment Setup'!X15/$I$27,0)*$J$27+IFERROR('Shipment Setup'!S15*'Shipment Setup'!X15/$I$28,0)*$J$28,0) -> 0 | H33: =IF(F33>0,G33/F33,0) -> 0
A34: AGL freight discount vs market (memo $) | B34: =IF(N(B33)>0,B33-B17,"") | E34: =IF('Shipment Setup'!A16="","",'Shipment Setup'!A16) | F34: =N('Shipment Setup'!B16) -> 0 | G34: =IF(N('Shipment Setup'!B16)>0,$F$43*'Shipment Setup'!Y16+'Shipment Setup'!O16+IFERROR('Shipment Setup'!P16*'Shipment Setup'!X16/$I$25,0)*$J$25+IFERROR('Shipment Setup'!Q16*'Shipment Setup'!X16/$I$26,0)*$J$26+IFERROR('Shipment Setup'!R16*'Shipment Setup'!X16/$I$27,0)*$J$27+IFERROR('Shipment Setup'!S16*'Shipment Setup'!X16/$I$28,0)*$J$28,0) -> 0 | H34: =IF(F34>0,G34/F34,0) -> 0
E35: =IF('Shipment Setup'!A17="","",'Shipment Setup'!A17) | F35: =N('Shipment Setup'!B17) -> 0 | G35: =IF(N('Shipment Setup'!B17)>0,$F$43*'Shipment Setup'!Y17+'Shipment Setup'!O17+IFERROR('Shipment Setup'!P17*'Shipment Setup'!X17/$I$25,0)*$J$25+IFERROR('Shipment Setup'!Q17*'Shipment Setup'!X17/$I$26,0)*$J$26+IFERROR('Shipment Setup'!R17*'Shipment Setup'!X17/$I$27,0)*$J$27+IFERROR('Shipment Setup'!S17*'Shipment Setup'!X17/$I$28,0)*$J$28,0) -> 0 | H35: =IF(F35>0,G35/F35,0) -> 0
E36: =IF('Shipment Setup'!A18="","",'Shipment Setup'!A18) | F36: =N('Shipment Setup'!B18) -> 0 | G36: =IF(N('Shipment Setup'!B18)>0,$F$43*'Shipment Setup'!Y18+'Shipment Setup'!O18+IFERROR('Shipment Setup'!P18*'Shipment Setup'!X18/$I$25,0)*$J$25+IFERROR('Shipment Setup'!Q18*'Shipment Setup'!X18/$I$26,0)*$J$26+IFERROR('Shipment Setup'!R18*'Shipment Setup'!X18/$I$27,0)*$J$27+IFERROR('Shipment Setup'!S18*'Shipment Setup'!X18/$I$28,0)*$J$28,0) -> 0 | H36: =IF(F36>0,G36/F36,0) -> 0
E37: =IF('Shipment Setup'!A19="","",'Shipment Setup'!A19) | F37: =N('Shipment Setup'!B19) -> 0 | G37: =IF(N('Shipment Setup'!B19)>0,$F$43*'Shipment Setup'!Y19+'Shipment Setup'!O19+IFERROR('Shipment Setup'!P19*'Shipment Setup'!X19/$I$25,0)*$J$25+IFERROR('Shipment Setup'!Q19*'Shipment Setup'!X19/$I$26,0)*$J$26+IFERROR('Shipment Setup'!R19*'Shipment Setup'!X19/$I$27,0)*$J$27+IFERROR('Shipment Setup'!S19*'Shipment Setup'!X19/$I$28,0)*$J$28,0) -> 0 | H37: =IF(F37>0,G37/F37,0) -> 0
E38: =IF('Shipment Setup'!A20="","",'Shipment Setup'!A20) | F38: =N('Shipment Setup'!B20) -> 0 | G38: =IF(N('Shipment Setup'!B20)>0,$F$43*'Shipment Setup'!Y20+'Shipment Setup'!O20+IFERROR('Shipment Setup'!P20*'Shipment Setup'!X20/$I$25,0)*$J$25+IFERROR('Shipment Setup'!Q20*'Shipment Setup'!X20/$I$26,0)*$J$26+IFERROR('Shipment Setup'!R20*'Shipment Setup'!X20/$I$27,0)*$J$27+IFERROR('Shipment Setup'!S20*'Shipment Setup'!X20/$I$28,0)*$J$28,0) -> 0 | H38: =IF(F38>0,G38/F38,0) -> 0
E39: =IF('Shipment Setup'!A21="","",'Shipment Setup'!A21) | F39: =N('Shipment Setup'!B21) -> 0 | G39: =IF(N('Shipment Setup'!B21)>0,$F$43*'Shipment Setup'!Y21+'Shipment Setup'!O21+IFERROR('Shipment Setup'!P21*'Shipment Setup'!X21/$I$25,0)*$J$25+IFERROR('Shipment Setup'!Q21*'Shipment Setup'!X21/$I$26,0)*$J$26+IFERROR('Shipment Setup'!R21*'Shipment Setup'!X21/$I$27,0)*$J$27+IFERROR('Shipment Setup'!S21*'Shipment Setup'!X21/$I$28,0)*$J$28,0) -> 0 | H39: =IF(F39>0,G39/F39,0) -> 0
E40: =IF('Shipment Setup'!A22="","",'Shipment Setup'!A22) | F40: =N('Shipment Setup'!B22) -> 0 | G40: =IF(N('Shipment Setup'!B22)>0,$F$43*'Shipment Setup'!Y22+'Shipment Setup'!O22+IFERROR('Shipment Setup'!P22*'Shipment Setup'!X22/$I$25,0)*$J$25+IFERROR('Shipment Setup'!Q22*'Shipment Setup'!X22/$I$26,0)*$J$26+IFERROR('Shipment Setup'!R22*'Shipment Setup'!X22/$I$27,0)*$J$27+IFERROR('Shipment Setup'!S22*'Shipment Setup'!X22/$I$28,0)*$J$28,0) -> 0 | H40: =IF(F40>0,G40/F40,0) -> 0
E41: =IF('Shipment Setup'!A23="","",'Shipment Setup'!A23) | F41: =N('Shipment Setup'!B23) -> 0 | G41: =IF(N('Shipment Setup'!B23)>0,$F$43*'Shipment Setup'!Y23+'Shipment Setup'!O23+IFERROR('Shipment Setup'!P23*'Shipment Setup'!X23/$I$25,0)*$J$25+IFERROR('Shipment Setup'!Q23*'Shipment Setup'!X23/$I$26,0)*$J$26+IFERROR('Shipment Setup'!R23*'Shipment Setup'!X23/$I$27,0)*$J$27+IFERROR('Shipment Setup'!S23*'Shipment Setup'!X23/$I$28,0)*$J$28,0) -> 0 | H41: =IF(F41>0,G41/F41,0) -> 0
E43: Shared cost pool (freight, origin, destination, hub, other) | F43: =F5+F6+F7+F14+F15 -> 0

Sheet Scenario 1
A1: SCENARIO 1 - THIRD-PARTY FREIGHT QUOTE
A2: Quote inputs are the source of truth for freight and tariff costs. Greyed rows do not apply to the chosen Incoterm / mode. Scenarios 1-3 have identical inputs.
A4: 1. QUOTE DETAILS | E4: RESULTS (output only)
A5: Forwarder / carrier | E5: Main freight / all-in quote | F5: =B20 -> 0
A6: Quote reference | E6: Origin charges | F6: =B25 -> 0
A7: Quote valid until | E7: Destination port, brokerage, insurance | F7: =B30 -> 0
A8: Incoterm | C8: EXW, FOB or DDP. DDP = duty included, no tariff entered | E8: Duty & tariff | F8: =B41 -> 0
A9: Mode | C9: FCL, LCL or Air | E9: Delivery to AWD | F9: =N(B32) -> 0
A10: Transit days (departure to arrival) | E10: Delivery / transfer to FBA | F10: =N(B33) -> 0
A11: Days from arrival to sellable stock | E11: Delivery / transfer to Walmart WFS | F11: =N(B34) -> 0
A12: 2. FREIGHT | E12: Delivery / transfer to TikTok FBT | F12: =N(B35) -> 0
A13: DDP all-in quote total ($) | C13: DDP only: door price incl. freight, duty, clearance | E13: Inbound placement fees | F13: =IF(B8="",0,N('Shipment Setup'!Q24)*N(B37)) -> 0
A14: FCL: number of containers | E14: Hub storage, handling & AWD fees | F14: =N(B38) -> 0
A15: FCL: price per container ($) | E15: Other fees | F15: =N(B39) -> 0
A16: LCL: rate per CBM ($) | E16: TOTAL LANDED COST (shipment) | F16: =SUM(F5:F15) -> 0
A17: LCL: minimum charge ($) | E17: Cost per unit | F17: =IF(N('Shipment Setup'!B24)>0,F16/'Shipment Setup'!B24,0) -> 0
A18: Air: rate per kg ($) | E18: Days: transit + to sellable | F18: =N(B10)+N(B11) -> 0
A19: Air: chargeable kg (calculated) | B19: =MAX('Shipment Setup'!H24,'Shipment Setup'!F24*'Rate Card'!B7) -> 0 | C19: Greater of actual kg and volumetric kg | E19: Cost of capital in transit (optional) | F19: =IF('Shipment Setup'!B8="Yes",F16*N('Shipment Setup'!B9)*F18/365,0) -> 0
A20: Main freight total (calculated) | B20: =IF(B8="DDP",N(B13),IF(B9="FCL",N(B14)*N(B15),IF(B9="LCL",MAX(N(B17),'Shipment Setup'!F24*N(B16)),IF(B9="Air",B19*N(B18),0)))) -> 0 | E20: Total incl. cost of capital | F20: =F16+F19 -> 0
A21: 3. ORIGIN CHARGES (EXW only) | E21: Cost per unit incl. capital | F21: =IF(N('Shipment Setup'!B24)>0,F20/'Shipment Setup'!B24,0) -> 0
A22: Factory pickup / trucking to port ($)
A23: Export customs clearance ($) | E23: BY DESTINATION
A24: Origin handling / THC / docs ($) | E24: Destination | F24: Units | G24: Total cost | H24: Cost / unit | I24: Alloc. weight | J24: Direct cost
A25: Origin total (calculated) | B25: =IF(B8="EXW",SUM(B22:B24),0) -> 0 | E25: AWD | F25: ='Shipment Setup'!P24 -> 500 | G25: =IFERROR($F$43*I25/SUMPRODUCT('Shipment Setup'!B14:B23,'Shipment Setup'!X14:X23),0)+J25+IF($B$8="DDP",0,SUMPRODUCT('Shipment Setup'!P14:P23,'Shipment Setup'!W14:W23)) -> 0 | H25: =IF(F25>0,G25/F25,0) -> 0 | I25: =SUMPRODUCT('Shipment Setup'!P14:P23,'Shipment Setup'!X14:X23) -> 0 | J25: =F9 -> 0
A26: 4. DESTINATION CHARGES (EXW and FOB; included in DDP) | E26: FBA direct | F26: ='Shipment Setup'!Q24 -> 250 | G26: =IFERROR($F$43*I26/SUMPRODUCT('Shipment Setup'!B14:B23,'Shipment Setup'!X14:X23),0)+J26+IF($B$8="DDP",0,SUMPRODUCT('Shipment Setup'!Q14:Q23,'Shipment Setup'!W14:W23)) -> 0 | H26: =IF(F26>0,G26/F26,0) -> 0 | I26: =SUMPRODUCT('Shipment Setup'!Q14:Q23,'Shipment Setup'!X14:X23) -> 0 | J26: =F10+F13 -> 0
A27: Destination port / terminal / drayage ($) | E27: Walmart WFS | F27: ='Shipment Setup'!R24 -> 100 | G27: =IFERROR($F$43*I27/SUMPRODUCT('Shipment Setup'!B14:B23,'Shipment Setup'!X14:X23),0)+J27+IF($B$8="DDP",0,SUMPRODUCT('Shipment Setup'!R14:R23,'Shipment Setup'!W14:W23)) -> 0 | H27: =IF(F27>0,G27/F27,0) -> 0 | I27: =SUMPRODUCT('Shipment Setup'!R14:R23,'Shipment Setup'!X14:X23) -> 0 | J27: =F11 -> 0
A28: Customs brokerage, ISF, bond ($) | E28: TikTok FBT | F28: ='Shipment Setup'!S24 -> 150 | G28: =IFERROR($F$43*I28/SUMPRODUCT('Shipment Setup'!B14:B23,'Shipment Setup'!X14:X23),0)+J28+IF($B$8="DDP",0,SUMPRODUCT('Shipment Setup'!S14:S23,'Shipment Setup'!W14:W23)) -> 0 | H28: =IF(F28>0,G28/F28,0) -> 0 | I28: =SUMPRODUCT('Shipment Setup'!S14:S23,'Shipment Setup'!X14:X23) -> 0 | J28: =F12 -> 0
A29: Cargo insurance ($)
A30: Destination total (calculated) | B30: =IF(B8="DDP",0,SUM(B27:B29)) -> 0 | E30: BY PRODUCT
A31: 5. DELIVERY TO EACH DESTINATION (total $ per destination) | E31: Product | F31: Units | G31: Total cost | H31: Cost / unit
A32: To AWD | E32: =IF('Shipment Setup'!A14="","",'Shipment Setup'!A14) -> Classic Food Mill | F32: =N('Shipment Setup'!B14) -> 1000 | G32: =IF(N('Shipment Setup'!B14)>0,$F$43*'Shipment Setup'!Y14+IF($B$8="DDP",0,'Shipment Setup'!O14)+IFERROR('Shipment Setup'!P14*'Shipment Setup'!X14/$I$25,0)*$J$25+IFERROR('Shipment Setup'!Q14*'Shipment Setup'!X14/$I$26,0)*$J$26+IFERROR('Shipment Setup'!R14*'Shipment Setup'!X14/$I$27,0)*$J$27+IFERROR('Shipment Setup'!S14*'Shipment Setup'!X14/$I$28,0)*$J$28,0) -> 0 | H32: =IF(F32>0,G32/F32,0) -> 0
A33: To FBA direct | E33: =IF('Shipment Setup'!A15="","",'Shipment Setup'!A15) | F33: =N('Shipment Setup'!B15) -> 0 | G33: =IF(N('Shipment Setup'!B15)>0,$F$43*'Shipment Setup'!Y15+IF($B$8="DDP",0,'Shipment Setup'!O15)+IFERROR('Shipment Setup'!P15*'Shipment Setup'!X15/$I$25,0)*$J$25+IFERROR('Shipment Setup'!Q15*'Shipment Setup'!X15/$I$26,0)*$J$26+IFERROR('Shipment Setup'!R15*'Shipment Setup'!X15/$I$27,0)*$J$27+IFERROR('Shipment Setup'!S15*'Shipment Setup'!X15/$I$28,0)*$J$28,0) -> 0 | H33: =IF(F33>0,G33/F33,0) -> 0
A34: To Walmart WFS | E34: =IF('Shipment Setup'!A16="","",'Shipment Setup'!A16) | F34: =N('Shipment Setup'!B16) -> 0 | G34: =IF(N('Shipment Setup'!B16)>0,$F$43*'Shipment Setup'!Y16+IF($B$8="DDP",0,'Shipment Setup'!O16)+IFERROR('Shipment Setup'!P16*'Shipment Setup'!X16/$I$25,0)*$J$25+IFERROR('Shipment Setup'!Q16*'Shipment Setup'!X16/$I$26,0)*$J$26+IFERROR('Shipment Setup'!R16*'Shipment Setup'!X16/$I$27,0)*$J$27+IFERROR('Shipment Setup'!S16*'Shipment Setup'!X16/$I$28,0)*$J$28,0) -> 0 | H34: =IF(F34>0,G34/F34,0) -> 0
A35: To TikTok FBT | E35: =IF('Shipment Setup'!A17="","",'Shipment Setup'!A17) | F35: =N('Shipment Setup'!B17) -> 0 | G35: =IF(N('Shipment Setup'!B17)>0,$F$43*'Shipment Setup'!Y17+IF($B$8="DDP",0,'Shipment Setup'!O17)+IFERROR('Shipment Setup'!P17*'Shipment Setup'!X17/$I$25,0)*$J$25+IFERROR('Shipment Setup'!Q17*'Shipment Setup'!X17/$I$26,0)*$J$26+IFERROR('Shipment Setup'!R17*'Shipment Setup'!X17/$I$27,0)*$J$27+IFERROR('Shipment Setup'!S17*'Shipment Setup'!X17/$I$28,0)*$J$28,0) -> 0 | H35: =IF(F35>0,G35/F35,0) -> 0
A36: 6. FEES AND STORAGE | E36: =IF('Shipment Setup'!A18="","",'Shipment Setup'!A18) | F36: =N('Shipment Setup'!B18) -> 0 | G36: =IF(N('Shipment Setup'!B18)>0,$F$43*'Shipment Setup'!Y18+IF($B$8="DDP",0,'Shipment Setup'!O18)+IFERROR('Shipment Setup'!P18*'Shipment Setup'!X18/$I$25,0)*$J$25+IFERROR('Shipment Setup'!Q18*'Shipment Setup'!X18/$I$26,0)*$J$26+IFERROR('Shipment Setup'!R18*'Shipment Setup'!X18/$I$27,0)*$J$27+IFERROR('Shipment Setup'!S18*'Shipment Setup'!X18/$I$28,0)*$J$28,0) -> 0 | H36: =IF(F36>0,G36/F36,0) -> 0
A37: Inbound placement fee per unit, FBA direct units ($) | B37: ='Rate Card'!B5 -> 0.5 | C37: Defaults to Rate Card; overwrite if quoted | E37: =IF('Shipment Setup'!A19="","",'Shipment Setup'!A19) | F37: =N('Shipment Setup'!B19) -> 0 | G37: =IF(N('Shipment Setup'!B19)>0,$F$43*'Shipment Setup'!Y19+IF($B$8="DDP",0,'Shipment Setup'!O19)+IFERROR('Shipment Setup'!P19*'Shipment Setup'!X19/$I$25,0)*$J$25+IFERROR('Shipment Setup'!Q19*'Shipment Setup'!X19/$I$26,0)*$J$26+IFERROR('Shipment Setup'!R19*'Shipment Setup'!X19/$I$27,0)*$J$27+IFERROR('Shipment Setup'!S19*'Shipment Setup'!X19/$I$28,0)*$J$28,0) -> 0 | H37: =IF(F37>0,G37/F37,0) -> 0
A38: 3PL / hub storage and handling total ($) | E38: =IF('Shipment Setup'!A20="","",'Shipment Setup'!A20) | F38: =N('Shipment Setup'!B20) -> 0 | G38: =IF(N('Shipment Setup'!B20)>0,$F$43*'Shipment Setup'!Y20+IF($B$8="DDP",0,'Shipment Setup'!O20)+IFERROR('Shipment Setup'!P20*'Shipment Setup'!X20/$I$25,0)*$J$25+IFERROR('Shipment Setup'!Q20*'Shipment Setup'!X20/$I$26,0)*$J$26+IFERROR('Shipment Setup'!R20*'Shipment Setup'!X20/$I$27,0)*$J$27+IFERROR('Shipment Setup'!S20*'Shipment Setup'!X20/$I$28,0)*$J$28,0) -> 0 | H38: =IF(F38>0,G38/F38,0) -> 0
A39: Other fees ($) | E39: =IF('Shipment Setup'!A21="","",'Shipment Setup'!A21) | F39: =N('Shipment Setup'!B21) -> 0 | G39: =IF(N('Shipment Setup'!B21)>0,$F$43*'Shipment Setup'!Y21+IF($B$8="DDP",0,'Shipment Setup'!O21)+IFERROR('Shipment Setup'!P21*'Shipment Setup'!X21/$I$25,0)*$J$25+IFERROR('Shipment Setup'!Q21*'Shipment Setup'!X21/$I$26,0)*$J$26+IFERROR('Shipment Setup'!R21*'Shipment Setup'!X21/$I$27,0)*$J$27+IFERROR('Shipment Setup'!S21*'Shipment Setup'!X21/$I$28,0)*$J$28,0) -> 0 | H39: =IF(F39>0,G39/F39,0) -> 0
A40: 7. DUTY AND TARIFF | E40: =IF('Shipment Setup'!A22="","",'Shipment Setup'!A22) | F40: =N('Shipment Setup'!B22) -> 0 | G40: =IF(N('Shipment Setup'!B22)>0,$F$43*'Shipment Setup'!Y22+IF($B$8="DDP",0,'Shipment Setup'!O22)+IFERROR('Shipment Setup'!P22*'Shipment Setup'!X22/$I$25,0)*$J$25+IFERROR('Shipment Setup'!Q22*'Shipment Setup'!X22/$I$26,0)*$J$26+IFERROR('Shipment Setup'!R22*'Shipment Setup'!X22/$I$27,0)*$J$27+IFERROR('Shipment Setup'!S22*'Shipment Setup'!X22/$I$28,0)*$J$28,0) -> 0 | H40: =IF(F40>0,G40/F40,0) -> 0
A41: Duty & tariff (calculated from Shipment Setup) | B41: =IF(OR(B8="",B8="DDP"),0,'Shipment Setup'!O24) -> 0 | C41: Zero if DDP | E41: =IF('Shipment Setup'!A23="","",'Shipment Setup'!A23) | F41: =N('Shipment Setup'!B23) -> 0 | G41: =IF(N('Shipment Setup'!B23)>0,$F$43*'Shipment Setup'!Y23+IF($B$8="DDP",0,'Shipment Setup'!O23)+IFERROR('Shipment Setup'!P23*'Shipment Setup'!X23/$I$25,0)*$J$25+IFERROR('Shipment Setup'!Q23*'Shipment Setup'!X23/$I$26,0)*$J$26+IFERROR('Shipment Setup'!R23*'Shipment Setup'!X23/$I$27,0)*$J$27+IFERROR('Shipment Setup'!S23*'Shipment Setup'!X23/$I$28,0)*$J$28,0) -> 0 | H41: =IF(F41>0,G41/F41,0) -> 0
E43: Shared cost pool (freight, origin, destination, hub, other) | F43: =F5+F6+F7+F14+F15 -> 0

Sheet Scenario 2
A1: SCENARIO 2 - THIRD-PARTY FREIGHT QUOTE
A2: Quote inputs are the source of truth for freight and tariff costs. Greyed rows do not apply to the chosen Incoterm / mode. Scenarios 1-3 have identical inputs.
A4: 1. QUOTE DETAILS | E4: RESULTS (output only)
A5: Forwarder / carrier | E5: Main freight / all-in quote | F5: =B20 -> 0
A6: Quote reference | E6: Origin charges | F6: =B25 -> 0
A7: Quote valid until | E7: Destination port, brokerage, insurance | F7: =B30 -> 0
A8: Incoterm | C8: EXW, FOB or DDP. DDP = duty included, no tariff entered | E8: Duty & tariff | F8: =B41 -> 0
A9: Mode | C9: FCL, LCL or Air | E9: Delivery to AWD | F9: =N(B32) -> 0
A10: Transit days (departure to arrival) | E10: Delivery / transfer to FBA | F10: =N(B33) -> 0
A11: Days from arrival to sellable stock | E11: Delivery / transfer to Walmart WFS | F11: =N(B34) -> 0
A12: 2. FREIGHT | E12: Delivery / transfer to TikTok FBT | F12: =N(B35) -> 0
A13: DDP all-in quote total ($) | C13: DDP only: door price incl. freight, duty, clearance | E13: Inbound placement fees | F13: =IF(B8="",0,N('Shipment Setup'!Q24)*N(B37)) -> 0
A14: FCL: number of containers | E14: Hub storage, handling & AWD fees | F14: =N(B38) -> 0
A15: FCL: price per container ($) | E15: Other fees | F15: =N(B39) -> 0
A16: LCL: rate per CBM ($) | E16: TOTAL LANDED COST (shipment) | F16: =SUM(F5:F15) -> 0
A17: LCL: minimum charge ($) | E17: Cost per unit | F17: =IF(N('Shipment Setup'!B24)>0,F16/'Shipment Setup'!B24,0) -> 0
A18: Air: rate per kg ($) | E18: Days: transit + to sellable | F18: =N(B10)+N(B11) -> 0
A19: Air: chargeable kg (calculated) | B19: =MAX('Shipment Setup'!H24,'Shipment Setup'!F24*'Rate Card'!B7) -> 0 | C19: Greater of actual kg and volumetric kg | E19: Cost of capital in transit (optional) | F19: =IF('Shipment Setup'!B8="Yes",F16*N('Shipment Setup'!B9)*F18/365,0) -> 0
A20: Main freight total (calculated) | B20: =IF(B8="DDP",N(B13),IF(B9="FCL",N(B14)*N(B15),IF(B9="LCL",MAX(N(B17),'Shipment Setup'!F24*N(B16)),IF(B9="Air",B19*N(B18),0)))) -> 0 | E20: Total incl. cost of capital | F20: =F16+F19 -> 0
A21: 3. ORIGIN CHARGES (EXW only) | E21: Cost per unit incl. capital | F21: =IF(N('Shipment Setup'!B24)>0,F20/'Shipment Setup'!B24,0) -> 0
A22: Factory pickup / trucking to port ($)
A23: Export customs clearance ($) | E23: BY DESTINATION
A24: Origin handling / THC / docs ($) | E24: Destination | F24: Units | G24: Total cost | H24: Cost / unit | I24: Alloc. weight | J24: Direct cost
A25: Origin total (calculated) | B25: =IF(B8="EXW",SUM(B22:B24),0) -> 0 | E25: AWD | F25: ='Shipment Setup'!P24 -> 500 | G25: =IFERROR($F$43*I25/SUMPRODUCT('Shipment Setup'!B14:B23,'Shipment Setup'!X14:X23),0)+J25+IF($B$8="DDP",0,SUMPRODUCT('Shipment Setup'!P14:P23,'Shipment Setup'!W14:W23)) -> 0 | H25: =IF(F25>0,G25/F25,0) -> 0 | I25: =SUMPRODUCT('Shipment Setup'!P14:P23,'Shipment Setup'!X14:X23) -> 0 | J25: =F9 -> 0
A26: 4. DESTINATION CHARGES (EXW and FOB; included in DDP) | E26: FBA direct | F26: ='Shipment Setup'!Q24 -> 250 | G26: =IFERROR($F$43*I26/SUMPRODUCT('Shipment Setup'!B14:B23,'Shipment Setup'!X14:X23),0)+J26+IF($B$8="DDP",0,SUMPRODUCT('Shipment Setup'!Q14:Q23,'Shipment Setup'!W14:W23)) -> 0 | H26: =IF(F26>0,G26/F26,0) -> 0 | I26: =SUMPRODUCT('Shipment Setup'!Q14:Q23,'Shipment Setup'!X14:X23) -> 0 | J26: =F10+F13 -> 0
A27: Destination port / terminal / drayage ($) | E27: Walmart WFS | F27: ='Shipment Setup'!R24 -> 100 | G27: =IFERROR($F$43*I27/SUMPRODUCT('Shipment Setup'!B14:B23,'Shipment Setup'!X14:X23),0)+J27+IF($B$8="DDP",0,SUMPRODUCT('Shipment Setup'!R14:R23,'Shipment Setup'!W14:W23)) -> 0 | H27: =IF(F27>0,G27/F27,0) -> 0 | I27: =SUMPRODUCT('Shipment Setup'!R14:R23,'Shipment Setup'!X14:X23) -> 0 | J27: =F11 -> 0
A28: Customs brokerage, ISF, bond ($) | E28: TikTok FBT | F28: ='Shipment Setup'!S24 -> 150 | G28: =IFERROR($F$43*I28/SUMPRODUCT('Shipment Setup'!B14:B23,'Shipment Setup'!X14:X23),0)+J28+IF($B$8="DDP",0,SUMPRODUCT('Shipment Setup'!S14:S23,'Shipment Setup'!W14:W23)) -> 0 | H28: =IF(F28>0,G28/F28,0) -> 0 | I28: =SUMPRODUCT('Shipment Setup'!S14:S23,'Shipment Setup'!X14:X23) -> 0 | J28: =F12 -> 0
A29: Cargo insurance ($)
A30: Destination total (calculated) | B30: =IF(B8="DDP",0,SUM(B27:B29)) -> 0 | E30: BY PRODUCT
A31: 5. DELIVERY TO EACH DESTINATION (total $ per destination) | E31: Product | F31: Units | G31: Total cost | H31: Cost / unit
A32: To AWD | E32: =IF('Shipment Setup'!A14="","",'Shipment Setup'!A14) -> Classic Food Mill | F32: =N('Shipment Setup'!B14) -> 1000 | G32: =IF(N('Shipment Setup'!B14)>0,$F$43*'Shipment Setup'!Y14+IF($B$8="DDP",0,'Shipment Setup'!O14)+IFERROR('Shipment Setup'!P14*'Shipment Setup'!X14/$I$25,0)*$J$25+IFERROR('Shipment Setup'!Q14*'Shipment Setup'!X14/$I$26,0)*$J$26+IFERROR('Shipment Setup'!R14*'Shipment Setup'!X14/$I$27,0)*$J$27+IFERROR('Shipment Setup'!S14*'Shipment Setup'!X14/$I$28,0)*$J$28,0) -> 0 | H32: =IF(F32>0,G32/F32,0) -> 0
A33: To FBA direct | E33: =IF('Shipment Setup'!A15="","",'Shipment Setup'!A15) | F33: =N('Shipment Setup'!B15) -> 0 | G33: =IF(N('Shipment Setup'!B15)>0,$F$43*'Shipment Setup'!Y15+IF($B$8="DDP",0,'Shipment Setup'!O15)+IFERROR('Shipment Setup'!P15*'Shipment Setup'!X15/$I$25,0)*$J$25+IFERROR('Shipment Setup'!Q15*'Shipment Setup'!X15/$I$26,0)*$J$26+IFERROR('Shipment Setup'!R15*'Shipment Setup'!X15/$I$27,0)*$J$27+IFERROR('Shipment Setup'!S15*'Shipment Setup'!X15/$I$28,0)*$J$28,0) -> 0 | H33: =IF(F33>0,G33/F33,0) -> 0
A34: To Walmart WFS | E34: =IF('Shipment Setup'!A16="","",'Shipment Setup'!A16) | F34: =N('Shipment Setup'!B16) -> 0 | G34: =IF(N('Shipment Setup'!B16)>0,$F$43*'Shipment Setup'!Y16+IF($B$8="DDP",0,'Shipment Setup'!O16)+IFERROR('Shipment Setup'!P16*'Shipment Setup'!X16/$I$25,0)*$J$25+IFERROR('Shipment Setup'!Q16*'Shipment Setup'!X16/$I$26,0)*$J$26+IFERROR('Shipment Setup'!R16*'Shipment Setup'!X16/$I$27,0)*$J$27+IFERROR('Shipment Setup'!S16*'Shipment Setup'!X16/$I$28,0)*$J$28,0) -> 0 | H34: =IF(F34>0,G34/F34,0) -> 0
A35: To TikTok FBT | E35: =IF('Shipment Setup'!A17="","",'Shipment Setup'!A17) | F35: =N('Shipment Setup'!B17) -> 0 | G35: =IF(N('Shipment Setup'!B17)>0,$F$43*'Shipment Setup'!Y17+IF($B$8="DDP",0,'Shipment Setup'!O17)+IFERROR('Shipment Setup'!P17*'Shipment Setup'!X17/$I$25,0)*$J$25+IFERROR('Shipment Setup'!Q17*'Shipment Setup'!X17/$I$26,0)*$J$26+IFERROR('Shipment Setup'!R17*'Shipment Setup'!X17/$I$27,0)*$J$27+IFERROR('Shipment Setup'!S17*'Shipment Setup'!X17/$I$28,0)*$J$28,0) -> 0 | H35: =IF(F35>0,G35/F35,0) -> 0
A36: 6. FEES AND STORAGE | E36: =IF('Shipment Setup'!A18="","",'Shipment Setup'!A18) | F36: =N('Shipment Setup'!B18) -> 0 | G36: =IF(N('Shipment Setup'!B18)>0,$F$43*'Shipment Setup'!Y18+IF($B$8="DDP",0,'Shipment Setup'!O18)+IFERROR('Shipment Setup'!P18*'Shipment Setup'!X18/$I$25,0)*$J$25+IFERROR('Shipment Setup'!Q18*'Shipment Setup'!X18/$I$26,0)*$J$26+IFERROR('Shipment Setup'!R18*'Shipment Setup'!X18/$I$27,0)*$J$27+IFERROR('Shipment Setup'!S18*'Shipment Setup'!X18/$I$28,0)*$J$28,0) -> 0 | H36: =IF(F36>0,G36/F36,0) -> 0
A37: Inbound placement fee per unit, FBA direct units ($) | B37: ='Rate Card'!B5 -> 0.5 | C37: Defaults to Rate Card; overwrite if quoted | E37: =IF('Shipment Setup'!A19="","",'Shipment Setup'!A19) | F37: =N('Shipment Setup'!B19) -> 0 | G37: =IF(N('Shipment Setup'!B19)>0,$F$43*'Shipment Setup'!Y19+IF($B$8="DDP",0,'Shipment Setup'!O19)+IFERROR('Shipment Setup'!P19*'Shipment Setup'!X19/$I$25,0)*$J$25+IFERROR('Shipment Setup'!Q19*'Shipment Setup'!X19/$I$26,0)*$J$26+IFERROR('Shipment Setup'!R19*'Shipment Setup'!X19/$I$27,0)*$J$27+IFERROR('Shipment Setup'!S19*'Shipment Setup'!X19/$I$28,0)*$J$28,0) -> 0 | H37: =IF(F37>0,G37/F37,0) -> 0
A38: 3PL / hub storage and handling total ($) | E38: =IF('Shipment Setup'!A20="","",'Shipment Setup'!A20) | F38: =N('Shipment Setup'!B20) -> 0 | G38: =IF(N('Shipment Setup'!B20)>0,$F$43*'Shipment Setup'!Y20+IF($B$8="DDP",0,'Shipment Setup'!O20)+IFERROR('Shipment Setup'!P20*'Shipment Setup'!X20/$I$25,0)*$J$25+IFERROR('Shipment Setup'!Q20*'Shipment Setup'!X20/$I$26,0)*$J$26+IFERROR('Shipment Setup'!R20*'Shipment Setup'!X20/$I$27,0)*$J$27+IFERROR('Shipment Setup'!S20*'Shipment Setup'!X20/$I$28,0)*$J$28,0) -> 0 | H38: =IF(F38>0,G38/F38,0) -> 0
A39: Other fees ($) | E39: =IF('Shipment Setup'!A21="","",'Shipment Setup'!A21) | F39: =N('Shipment Setup'!B21) -> 0 | G39: =IF(N('Shipment Setup'!B21)>0,$F$43*'Shipment Setup'!Y21+IF($B$8="DDP",0,'Shipment Setup'!O21)+IFERROR('Shipment Setup'!P21*'Shipment Setup'!X21/$I$25,0)*$J$25+IFERROR('Shipment Setup'!Q21*'Shipment Setup'!X21/$I$26,0)*$J$26+IFERROR('Shipment Setup'!R21*'Shipment Setup'!X21/$I$27,0)*$J$27+IFERROR('Shipment Setup'!S21*'Shipment Setup'!X21/$I$28,0)*$J$28,0) -> 0 | H39: =IF(F39>0,G39/F39,0) -> 0
A40: 7. DUTY AND TARIFF | E40: =IF('Shipment Setup'!A22="","",'Shipment Setup'!A22) | F40: =N('Shipment Setup'!B22) -> 0 | G40: =IF(N('Shipment Setup'!B22)>0,$F$43*'Shipment Setup'!Y22+IF($B$8="DDP",0,'Shipment Setup'!O22)+IFERROR('Shipment Setup'!P22*'Shipment Setup'!X22/$I$25,0)*$J$25+IFERROR('Shipment Setup'!Q22*'Shipment Setup'!X22/$I$26,0)*$J$26+IFERROR('Shipment Setup'!R22*'Shipment Setup'!X22/$I$27,0)*$J$27+IFERROR('Shipment Setup'!S22*'Shipment Setup'!X22/$I$28,0)*$J$28,0) -> 0 | H40: =IF(F40>0,G40/F40,0) -> 0
A41: Duty & tariff (calculated from Shipment Setup) | B41: =IF(OR(B8="",B8="DDP"),0,'Shipment Setup'!O24) -> 0 | C41: Zero if DDP | E41: =IF('Shipment Setup'!A23="","",'Shipment Setup'!A23) | F41: =N('Shipment Setup'!B23) -> 0 | G41: =IF(N('Shipment Setup'!B23)>0,$F$43*'Shipment Setup'!Y23+IF($B$8="DDP",0,'Shipment Setup'!O23)+IFERROR('Shipment Setup'!P23*'Shipment Setup'!X23/$I$25,0)*$J$25+IFERROR('Shipment Setup'!Q23*'Shipment Setup'!X23/$I$26,0)*$J$26+IFERROR('Shipment Setup'!R23*'Shipment Setup'!X23/$I$27,0)*$J$27+IFERROR('Shipment Setup'!S23*'Shipment Setup'!X23/$I$28,0)*$J$28,0) -> 0 | H41: =IF(F41>0,G41/F41,0) -> 0
E43: Shared cost pool (freight, origin, destination, hub, other) | F43: =F5+F6+F7+F14+F15 -> 0

Sheet Scenario 3
A1: SCENARIO 3 - THIRD-PARTY FREIGHT QUOTE
A2: Quote inputs are the source of truth for freight and tariff costs. Greyed rows do not apply to the chosen Incoterm / mode. Scenarios 1-3 have identical inputs.
A4: 1. QUOTE DETAILS | E4: RESULTS (output only)
A5: Forwarder / carrier | E5: Main freight / all-in quote | F5: =B20 -> 0
A6: Quote reference | E6: Origin charges | F6: =B25 -> 0
A7: Quote valid until | E7: Destination port, brokerage, insurance | F7: =B30 -> 0
A8: Incoterm | C8: EXW, FOB or DDP. DDP = duty included, no tariff entered | E8: Duty & tariff | F8: =B41 -> 0
A9: Mode | C9: FCL, LCL or Air | E9: Delivery to AWD | F9: =N(B32) -> 0
A10: Transit days (departure to arrival) | E10: Delivery / transfer to FBA | F10: =N(B33) -> 0
A11: Days from arrival to sellable stock | E11: Delivery / transfer to Walmart WFS | F11: =N(B34) -> 0
A12: 2. FREIGHT | E12: Delivery / transfer to TikTok FBT | F12: =N(B35) -> 0
A13: DDP all-in quote total ($) | C13: DDP only: door price incl. freight, duty, clearance | E13: Inbound placement fees | F13: =IF(B8="",0,N('Shipment Setup'!Q24)*N(B37)) -> 0
A14: FCL: number of containers | E14: Hub storage, handling & AWD fees | F14: =N(B38) -> 0
A15: FCL: price per container ($) | E15: Other fees | F15: =N(B39) -> 0
A16: LCL: rate per CBM ($) | E16: TOTAL LANDED COST (shipment) | F16: =SUM(F5:F15) -> 0
A17: LCL: minimum charge ($) | E17: Cost per unit | F17: =IF(N('Shipment Setup'!B24)>0,F16/'Shipment Setup'!B24,0) -> 0
A18: Air: rate per kg ($) | E18: Days: transit + to sellable | F18: =N(B10)+N(B11) -> 0
A19: Air: chargeable kg (calculated) | B19: =MAX('Shipment Setup'!H24,'Shipment Setup'!F24*'Rate Card'!B7) -> 0 | C19: Greater of actual kg and volumetric kg | E19: Cost of capital in transit (optional) | F19: =IF('Shipment Setup'!B8="Yes",F16*N('Shipment Setup'!B9)*F18/365,0) -> 0
A20: Main freight total (calculated) | B20: =IF(B8="DDP",N(B13),IF(B9="FCL",N(B14)*N(B15),IF(B9="LCL",MAX(N(B17),'Shipment Setup'!F24*N(B16)),IF(B9="Air",B19*N(B18),0)))) -> 0 | E20: Total incl. cost of capital | F20: =F16+F19 -> 0
A21: 3. ORIGIN CHARGES (EXW only) | E21: Cost per unit incl. capital | F21: =IF(N('Shipment Setup'!B24)>0,F20/'Shipment Setup'!B24,0) -> 0
A22: Factory pickup / trucking to port ($)
A23: Export customs clearance ($) | E23: BY DESTINATION
A24: Origin handling / THC / docs ($) | E24: Destination | F24: Units | G24: Total cost | H24: Cost / unit | I24: Alloc. weight | J24: Direct cost
A25: Origin total (calculated) | B25: =IF(B8="EXW",SUM(B22:B24),0) -> 0 | E25: AWD | F25: ='Shipment Setup'!P24 -> 500 | G25: =IFERROR($F$43*I25/SUMPRODUCT('Shipment Setup'!B14:B23,'Shipment Setup'!X14:X23),0)+J25+IF($B$8="DDP",0,SUMPRODUCT('Shipment Setup'!P14:P23,'Shipment Setup'!W14:W23)) -> 0 | H25: =IF(F25>0,G25/F25,0) -> 0 | I25: =SUMPRODUCT('Shipment Setup'!P14:P23,'Shipment Setup'!X14:X23) -> 0 | J25: =F9 -> 0
A26: 4. DESTINATION CHARGES (EXW and FOB; included in DDP) | E26: FBA direct | F26: ='Shipment Setup'!Q24 -> 250 | G26: =IFERROR($F$43*I26/SUMPRODUCT('Shipment Setup'!B14:B23,'Shipment Setup'!X14:X23),0)+J26+IF($B$8="DDP",0,SUMPRODUCT('Shipment Setup'!Q14:Q23,'Shipment Setup'!W14:W23)) -> 0 | H26: =IF(F26>0,G26/F26,0) -> 0 | I26: =SUMPRODUCT('Shipment Setup'!Q14:Q23,'Shipment Setup'!X14:X23) -> 0 | J26: =F10+F13 -> 0
A27: Destination port / terminal / drayage ($) | E27: Walmart WFS | F27: ='Shipment Setup'!R24 -> 100 | G27: =IFERROR($F$43*I27/SUMPRODUCT('Shipment Setup'!B14:B23,'Shipment Setup'!X14:X23),0)+J27+IF($B$8="DDP",0,SUMPRODUCT('Shipment Setup'!R14:R23,'Shipment Setup'!W14:W23)) -> 0 | H27: =IF(F27>0,G27/F27,0) -> 0 | I27: =SUMPRODUCT('Shipment Setup'!R14:R23,'Shipment Setup'!X14:X23) -> 0 | J27: =F11 -> 0
A28: Customs brokerage, ISF, bond ($) | E28: TikTok FBT | F28: ='Shipment Setup'!S24 -> 150 | G28: =IFERROR($F$43*I28/SUMPRODUCT('Shipment Setup'!B14:B23,'Shipment Setup'!X14:X23),0)+J28+IF($B$8="DDP",0,SUMPRODUCT('Shipment Setup'!S14:S23,'Shipment Setup'!W14:W23)) -> 0 | H28: =IF(F28>0,G28/F28,0) -> 0 | I28: =SUMPRODUCT('Shipment Setup'!S14:S23,'Shipment Setup'!X14:X23) -> 0 | J28: =F12 -> 0
A29: Cargo insurance ($)
A30: Destination total (calculated) | B30: =IF(B8="DDP",0,SUM(B27:B29)) -> 0 | E30: BY PRODUCT
A31: 5. DELIVERY TO EACH DESTINATION (total $ per destination) | E31: Product | F31: Units | G31: Total cost | H31: Cost / unit
A32: To AWD | E32: =IF('Shipment Setup'!A14="","",'Shipment Setup'!A14) -> Classic Food Mill | F32: =N('Shipment Setup'!B14) -> 1000 | G32: =IF(N('Shipment Setup'!B14)>0,$F$43*'Shipment Setup'!Y14+IF($B$8="DDP",0,'Shipment Setup'!O14)+IFERROR('Shipment Setup'!P14*'Shipment Setup'!X14/$I$25,0)*$J$25+IFERROR('Shipment Setup'!Q14*'Shipment Setup'!X14/$I$26,0)*$J$26+IFERROR('Shipment Setup'!R14*'Shipment Setup'!X14/$I$27,0)*$J$27+IFERROR('Shipment Setup'!S14*'Shipment Setup'!X14/$I$28,0)*$J$28,0) -> 0 | H32: =IF(F32>0,G32/F32,0) -> 0
A33: To FBA direct | E33: =IF('Shipment Setup'!A15="","",'Shipment Setup'!A15) | F33: =N('Shipment Setup'!B15) -> 0 | G33: =IF(N('Shipment Setup'!B15)>0,$F$43*'Shipment Setup'!Y15+IF($B$8="DDP",0,'Shipment Setup'!O15)+IFERROR('Shipment Setup'!P15*'Shipment Setup'!X15/$I$25,0)*$J$25+IFERROR('Shipment Setup'!Q15*'Shipment Setup'!X15/$I$26,0)*$J$26+IFERROR('Shipment Setup'!R15*'Shipment Setup'!X15/$I$27,0)*$J$27+IFERROR('Shipment Setup'!S15*'Shipment Setup'!X15/$I$28,0)*$J$28,0) -> 0 | H33: =IF(F33>0,G33/F33,0) -> 0
A34: To Walmart WFS | E34: =IF('Shipment Setup'!A16="","",'Shipment Setup'!A16) | F34: =N('Shipment Setup'!B16) -> 0 | G34: =IF(N('Shipment Setup'!B16)>0,$F$43*'Shipment Setup'!Y16+IF($B$8="DDP",0,'Shipment Setup'!O16)+IFERROR('Shipment Setup'!P16*'Shipment Setup'!X16/$I$25,0)*$J$25+IFERROR('Shipment Setup'!Q16*'Shipment Setup'!X16/$I$26,0)*$J$26+IFERROR('Shipment Setup'!R16*'Shipment Setup'!X16/$I$27,0)*$J$27+IFERROR('Shipment Setup'!S16*'Shipment Setup'!X16/$I$28,0)*$J$28,0) -> 0 | H34: =IF(F34>0,G34/F34,0) -> 0
A35: To TikTok FBT | E35: =IF('Shipment Setup'!A17="","",'Shipment Setup'!A17) | F35: =N('Shipment Setup'!B17) -> 0 | G35: =IF(N('Shipment Setup'!B17)>0,$F$43*'Shipment Setup'!Y17+IF($B$8="DDP",0,'Shipment Setup'!O17)+IFERROR('Shipment Setup'!P17*'Shipment Setup'!X17/$I$25,0)*$J$25+IFERROR('Shipment Setup'!Q17*'Shipment Setup'!X17/$I$26,0)*$J$26+IFERROR('Shipment Setup'!R17*'Shipment Setup'!X17/$I$27,0)*$J$27+IFERROR('Shipment Setup'!S17*'Shipment Setup'!X17/$I$28,0)*$J$28,0) -> 0 | H35: =IF(F35>0,G35/F35,0) -> 0
A36: 6. FEES AND STORAGE | E36: =IF('Shipment Setup'!A18="","",'Shipment Setup'!A18) | F36: =N('Shipment Setup'!B18) -> 0 | G36: =IF(N('Shipment Setup'!B18)>0,$F$43*'Shipment Setup'!Y18+IF($B$8="DDP",0,'Shipment Setup'!O18)+IFERROR('Shipment Setup'!P18*'Shipment Setup'!X18/$I$25,0)*$J$25+IFERROR('Shipment Setup'!Q18*'Shipment Setup'!X18/$I$26,0)*$J$26+IFERROR('Shipment Setup'!R18*'Shipment Setup'!X18/$I$27,0)*$J$27+IFERROR('Shipment Setup'!S18*'Shipment Setup'!X18/$I$28,0)*$J$28,0) -> 0 | H36: =IF(F36>0,G36/F36,0) -> 0
A37: Inbound placement fee per unit, FBA direct units ($) | B37: ='Rate Card'!B5 -> 0.5 | C37: Defaults to Rate Card; overwrite if quoted | E37: =IF('Shipment Setup'!A19="","",'Shipment Setup'!A19) | F37: =N('Shipment Setup'!B19) -> 0 | G37: =IF(N('Shipment Setup'!B19)>0,$F$43*'Shipment Setup'!Y19+IF($B$8="DDP",0,'Shipment Setup'!O19)+IFERROR('Shipment Setup'!P19*'Shipment Setup'!X19/$I$25,0)*$J$25+IFERROR('Shipment Setup'!Q19*'Shipment Setup'!X19/$I$26,0)*$J$26+IFERROR('Shipment Setup'!R19*'Shipment Setup'!X19/$I$27,0)*$J$27+IFERROR('Shipment Setup'!S19*'Shipment Setup'!X19/$I$28,0)*$J$28,0) -> 0 | H37: =IF(F37>0,G37/F37,0) -> 0
A38: 3PL / hub storage and handling total ($) | E38: =IF('Shipment Setup'!A20="","",'Shipment Setup'!A20) | F38: =N('Shipment Setup'!B20) -> 0 | G38: =IF(N('Shipment Setup'!B20)>0,$F$43*'Shipment Setup'!Y20+IF($B$8="DDP",0,'Shipment Setup'!O20)+IFERROR('Shipment Setup'!P20*'Shipment Setup'!X20/$I$25,0)*$J$25+IFERROR('Shipment Setup'!Q20*'Shipment Setup'!X20/$I$26,0)*$J$26+IFERROR('Shipment Setup'!R20*'Shipment Setup'!X20/$I$27,0)*$J$27+IFERROR('Shipment Setup'!S20*'Shipment Setup'!X20/$I$28,0)*$J$28,0) -> 0 | H38: =IF(F38>0,G38/F38,0) -> 0
A39: Other fees ($) | E39: =IF('Shipment Setup'!A21="","",'Shipment Setup'!A21) | F39: =N('Shipment Setup'!B21) -> 0 | G39: =IF(N('Shipment Setup'!B21)>0,$F$43*'Shipment Setup'!Y21+IF($B$8="DDP",0,'Shipment Setup'!O21)+IFERROR('Shipment Setup'!P21*'Shipment Setup'!X21/$I$25,0)*$J$25+IFERROR('Shipment Setup'!Q21*'Shipment Setup'!X21/$I$26,0)*$J$26+IFERROR('Shipment Setup'!R21*'Shipment Setup'!X21/$I$27,0)*$J$27+IFERROR('Shipment Setup'!S21*'Shipment Setup'!X21/$I$28,0)*$J$28,0) -> 0 | H39: =IF(F39>0,G39/F39,0) -> 0
A40: 7. DUTY AND TARIFF | E40: =IF('Shipment Setup'!A22="","",'Shipment Setup'!A22) | F40: =N('Shipment Setup'!B22) -> 0 | G40: =IF(N('Shipment Setup'!B22)>0,$F$43*'Shipment Setup'!Y22+IF($B$8="DDP",0,'Shipment Setup'!O22)+IFERROR('Shipment Setup'!P22*'Shipment Setup'!X22/$I$25,0)*$J$25+IFERROR('Shipment Setup'!Q22*'Shipment Setup'!X22/$I$26,0)*$J$26+IFERROR('Shipment Setup'!R22*'Shipment Setup'!X22/$I$27,0)*$J$27+IFERROR('Shipment Setup'!S22*'Shipment Setup'!X22/$I$28,0)*$J$28,0) -> 0 | H40: =IF(F40>0,G40/F40,0) -> 0
A41: Duty & tariff (calculated from Shipment Setup) | B41: =IF(OR(B8="",B8="DDP"),0,'Shipment Setup'!O24) -> 0 | C41: Zero if DDP | E41: =IF('Shipment Setup'!A23="","",'Shipment Setup'!A23) | F41: =N('Shipment Setup'!B23) -> 0 | G41: =IF(N('Shipment Setup'!B23)>0,$F$43*'Shipment Setup'!Y23+IF($B$8="DDP",0,'Shipment Setup'!O23)+IFERROR('Shipment Setup'!P23*'Shipment Setup'!X23/$I$25,0)*$J$25+IFERROR('Shipment Setup'!Q23*'Shipment Setup'!X23/$I$26,0)*$J$26+IFERROR('Shipment Setup'!R23*'Shipment Setup'!X23/$I$27,0)*$J$27+IFERROR('Shipment Setup'!S23*'Shipment Setup'!X23/$I$28,0)*$J$28,0) -> 0 | H41: =IF(F41>0,G41/F41,0) -> 0
E43: Shared cost pool (freight, origin, destination, hub, other) | F43: =F5+F6+F7+F14+F15 -> 0

Sheet Comparison
A1: SHIPMENT COST COMPARISON
A2: Output only. Total cost to ship this shipment through the Amazon AGL path and Scenarios 1-3. No product profitability here.
A4: SHIPMENT
A5: Shipment | B5: ='Shipment Setup'!B5
A6: Units | B6: ='Shipment Setup'!B24 -> 1000
A7: Total CBM | B7: ='Shipment Setup'!F24 -> 0
A8: Total kg | B8: ='Shipment Setup'!H24 -> 0
A10: Line | B10: Amazon: AGL > AWD | C10: Scenario 1 | D10: Scenario 2 | E10: Scenario 3
A11: Carrier / forwarder | B11: ="Amazon Global Logistics" -> Amazon Global Logistics | C11: =IF('Scenario 1'!B5="","",'Scenario 1'!B5) | D11: =IF('Scenario 2'!B5="","",'Scenario 2'!B5) | E11: =IF('Scenario 3'!B5="","",'Scenario 3'!B5)
A12: Incoterm | B12: ="AGL (duty separate)" -> AGL (duty separate) | C12: =IF('Scenario 1'!B8="","",'Scenario 1'!B8) | D12: =IF('Scenario 2'!B8="","",'Scenario 2'!B8) | E12: =IF('Scenario 3'!B8="","",'Scenario 3'!B8)
A13: Mode | B13: ='Amazon Path (AGL)'!B7 | C13: =IF('Scenario 1'!B9="","",'Scenario 1'!B9) | D13: =IF('Scenario 2'!B9="","",'Scenario 2'!B9) | E13: =IF('Scenario 3'!B9="","",'Scenario 3'!B9)
A14: Days: transit + to sellable | B14: ='Amazon Path (AGL)'!F18 -> 0 | C14: ='Scenario 1'!F18 -> 0 | D14: ='Scenario 2'!F18 -> 0 | E14: ='Scenario 3'!F18 -> 0
A15: Quote valid until | B15: ='Amazon Path (AGL)'!B6 | C15: =IF('Scenario 1'!B7="","",'Scenario 1'!B7) | D15: =IF('Scenario 2'!B7="","",'Scenario 2'!B7) | E15: =IF('Scenario 3'!B7="","",'Scenario 3'!B7)
A16: COST LINES (total $ for the shipment)
A17: Main freight / all-in quote | B17: ='Amazon Path (AGL)'!F5 -> 0 | C17: ='Scenario 1'!F5 -> 0 | D17: ='Scenario 2'!F5 -> 0 | E17: ='Scenario 3'!F5 -> 0
A18: Origin charges | B18: ='Amazon Path (AGL)'!F6 -> 0 | C18: ='Scenario 1'!F6 -> 0 | D18: ='Scenario 2'!F6 -> 0 | E18: ='Scenario 3'!F6 -> 0
A19: Destination port, brokerage, insurance | B19: ='Amazon Path (AGL)'!F7 -> 0 | C19: ='Scenario 1'!F7 -> 0 | D19: ='Scenario 2'!F7 -> 0 | E19: ='Scenario 3'!F7 -> 0
A20: Duty & tariff | B20: ='Amazon Path (AGL)'!F8 -> 0 | C20: ='Scenario 1'!F8 -> 0 | D20: ='Scenario 2'!F8 -> 0 | E20: ='Scenario 3'!F8 -> 0
A21: Delivery to AWD | B21: ='Amazon Path (AGL)'!F9 -> 0 | C21: ='Scenario 1'!F9 -> 0 | D21: ='Scenario 2'!F9 -> 0 | E21: ='Scenario 3'!F9 -> 0
A22: Delivery / transfer to FBA | B22: ='Amazon Path (AGL)'!F10 -> 0 | C22: ='Scenario 1'!F10 -> 0 | D22: ='Scenario 2'!F10 -> 0 | E22: ='Scenario 3'!F10 -> 0
A23: Delivery / transfer to Walmart WFS | B23: ='Amazon Path (AGL)'!F11 -> 0 | C23: ='Scenario 1'!F11 -> 0 | D23: ='Scenario 2'!F11 -> 0 | E23: ='Scenario 3'!F11 -> 0
A24: Delivery / transfer to TikTok FBT | B24: ='Amazon Path (AGL)'!F12 -> 0 | C24: ='Scenario 1'!F12 -> 0 | D24: ='Scenario 2'!F12 -> 0 | E24: ='Scenario 3'!F12 -> 0
A25: Inbound placement fees | B25: ='Amazon Path (AGL)'!F13 -> 0 | C25: ='Scenario 1'!F13 -> 0 | D25: ='Scenario 2'!F13 -> 0 | E25: ='Scenario 3'!F13 -> 0
A26: Hub storage, handling & AWD fees | B26: ='Amazon Path (AGL)'!F14 -> 0 | C26: ='Scenario 1'!F14 -> 0 | D26: ='Scenario 2'!F14 -> 0 | E26: ='Scenario 3'!F14 -> 0
A27: Other fees | B27: ='Amazon Path (AGL)'!F15 -> 0 | C27: ='Scenario 1'!F15 -> 0 | D27: ='Scenario 2'!F15 -> 0 | E27: ='Scenario 3'!F15 -> 0
A28: TOTAL LANDED COST | B28: ='Amazon Path (AGL)'!F16 -> 0 | C28: ='Scenario 1'!F16 -> 0 | D28: ='Scenario 2'!F16 -> 0 | E28: ='Scenario 3'!F16 -> 0
A29: Cost per unit | B29: ='Amazon Path (AGL)'!F17 -> 0 | C29: ='Scenario 1'!F17 -> 0 | D29: ='Scenario 2'!F17 -> 0 | E29: ='Scenario 3'!F17 -> 0
A30: Difference vs Amazon path ($) | C30: =IF(OR(C28=0,$B28=0),"",C28-$B28) | D30: =IF(OR(D28=0,$B28=0),"",D28-$B28) | E30: =IF(OR(E28=0,$B28=0),"",E28-$B28)
A31: Difference vs Amazon path (%) | C31: =IF(OR(C28=0,$B28=0),"",C28/$B28-1) | D31: =IF(OR(D28=0,$B28=0),"",D28/$B28-1) | E31: =IF(OR(E28=0,$B28=0),"",E28/$B28-1)
A32: Cost of capital in transit (optional) | B32: ='Amazon Path (AGL)'!F19 -> 0 | C32: ='Scenario 1'!F19 -> 0 | D32: ='Scenario 2'!F19 -> 0 | E32: ='Scenario 3'!F19 -> 0
A33: Total incl. cost of capital | B33: ='Amazon Path (AGL)'!F20 -> 0 | C33: ='Scenario 1'!F20 -> 0 | D33: ='Scenario 2'!F20 -> 0 | E33: ='Scenario 3'!F20 -> 0
A34: Cost per unit incl. capital | B34: ='Amazon Path (AGL)'!F21 -> 0 | C34: ='Scenario 1'!F21 -> 0 | D34: ='Scenario 2'!F21 -> 0 | E34: ='Scenario 3'!F21 -> 0
A35: Cheapest (incl. capital if switched on) | B35: =IF(B33=0,"",IF(B33=SMALL($B$33:$E$33,COUNTIF($B$33:$E$33,0)+1),"CHEAPEST","")) | C35: =IF(C33=0,"",IF(C33=SMALL($B$33:$E$33,COUNTIF($B$33:$E$33,0)+1),"CHEAPEST","")) | D35: =IF(D33=0,"",IF(D33=SMALL($B$33:$E$33,COUNTIF($B$33:$E$33,0)+1),"CHEAPEST","")) | E35: =IF(E33=0,"",IF(E33=SMALL($B$33:$E$33,COUNTIF($B$33:$E$33,0)+1),"CHEAPEST",""))
A36: Fastest (days to sellable) | B36: =IF(B14=0,"",IF(B14=SMALL($B$14:$E$14,COUNTIF($B$14:$E$14,0)+1),"FASTEST","")) | C36: =IF(C14=0,"",IF(C14=SMALL($B$14:$E$14,COUNTIF($B$14:$E$14,0)+1),"FASTEST","")) | D36: =IF(D14=0,"",IF(D14=SMALL($B$14:$E$14,COUNTIF($B$14:$E$14,0)+1),"FASTEST","")) | E36: =IF(E14=0,"",IF(E14=SMALL($B$14:$E$14,COUNTIF($B$14:$E$14,0)+1),"FASTEST",""))
A38: COST PER UNIT BY DESTINATION
A39: Destination | B39: Amazon | C39: Scenario 1 | D39: Scenario 2 | E39: Scenario 3
A40: AWD | B40: =IF('Amazon Path (AGL)'!F25=0,"",'Amazon Path (AGL)'!H25) -> 0 | C40: =IF('Scenario 1'!F25=0,"",'Scenario 1'!H25) -> 0 | D40: =IF('Scenario 2'!F25=0,"",'Scenario 2'!H25) -> 0 | E40: =IF('Scenario 3'!F25=0,"",'Scenario 3'!H25) -> 0
A41: FBA direct | B41: =IF('Amazon Path (AGL)'!F26=0,"",'Amazon Path (AGL)'!H26) -> 0 | C41: =IF('Scenario 1'!F26=0,"",'Scenario 1'!H26) -> 0 | D41: =IF('Scenario 2'!F26=0,"",'Scenario 2'!H26) -> 0 | E41: =IF('Scenario 3'!F26=0,"",'Scenario 3'!H26) -> 0
A42: Walmart WFS | B42: =IF('Amazon Path (AGL)'!F27=0,"",'Amazon Path (AGL)'!H27) -> 0 | C42: =IF('Scenario 1'!F27=0,"",'Scenario 1'!H27) -> 0 | D42: =IF('Scenario 2'!F27=0,"",'Scenario 2'!H27) -> 0 | E42: =IF('Scenario 3'!F27=0,"",'Scenario 3'!H27) -> 0
A43: TikTok FBT | B43: =IF('Amazon Path (AGL)'!F28=0,"",'Amazon Path (AGL)'!H28) -> 0 | C43: =IF('Scenario 1'!F28=0,"",'Scenario 1'!H28) -> 0 | D43: =IF('Scenario 2'!F28=0,"",'Scenario 2'!H28) -> 0 | E43: =IF('Scenario 3'!F28=0,"",'Scenario 3'!H28) -> 0
A45: COST PER UNIT BY PRODUCT
A46: Product | B46: Amazon | C46: Scenario 1 | D46: Scenario 2 | E46: Scenario 3
A47: ='Shipment Setup'!A14&"" -> Classic Food Mill | B47: =IF(N('Amazon Path (AGL)'!F32)=0,"",'Amazon Path (AGL)'!H32) -> 0 | C47: =IF(N('Scenario 1'!F32)=0,"",'Scenario 1'!H32) -> 0 | D47: =IF(N('Scenario 2'!F32)=0,"",'Scenario 2'!H32) -> 0 | E47: =IF(N('Scenario 3'!F32)=0,"",'Scenario 3'!H32) -> 0
A48: ='Shipment Setup'!A15&"" | B48: =IF(N('Amazon Path (AGL)'!F33)=0,"",'Amazon Path (AGL)'!H33) | C48: =IF(N('Scenario 1'!F33)=0,"",'Scenario 1'!H33) | D48: =IF(N('Scenario 2'!F33)=0,"",'Scenario 2'!H33) | E48: =IF(N('Scenario 3'!F33)=0,"",'Scenario 3'!H33)
A49: ='Shipment Setup'!A16&"" | B49: =IF(N('Amazon Path (AGL)'!F34)=0,"",'Amazon Path (AGL)'!H34) | C49: =IF(N('Scenario 1'!F34)=0,"",'Scenario 1'!H34) | D49: =IF(N('Scenario 2'!F34)=0,"",'Scenario 2'!H34) | E49: =IF(N('Scenario 3'!F34)=0,"",'Scenario 3'!H34)
A50: ='Shipment Setup'!A17&"" | B50: =IF(N('Amazon Path (AGL)'!F35)=0,"",'Amazon Path (AGL)'!H35) | C50: =IF(N('Scenario 1'!F35)=0,"",'Scenario 1'!H35) | D50: =IF(N('Scenario 2'!F35)=0,"",'Scenario 2'!H35) | E50: =IF(N('Scenario 3'!F35)=0,"",'Scenario 3'!H35)
A51: ='Shipment Setup'!A18&"" | B51: =IF(N('Amazon Path (AGL)'!F36)=0,"",'Amazon Path (AGL)'!H36) | C51: =IF(N('Scenario 1'!F36)=0,"",'Scenario 1'!H36) | D51: =IF(N('Scenario 2'!F36)=0,"",'Scenario 2'!H36) | E51: =IF(N('Scenario 3'!F36)=0,"",'Scenario 3'!H36)
A52: ='Shipment Setup'!A19&"" | B52: =IF(N('Amazon Path (AGL)'!F37)=0,"",'Amazon Path (AGL)'!H37) | C52: =IF(N('Scenario 1'!F37)=0,"",'Scenario 1'!H37) | D52: =IF(N('Scenario 2'!F37)=0,"",'Scenario 2'!H37) | E52: =IF(N('Scenario 3'!F37)=0,"",'Scenario 3'!H37)
A53: ='Shipment Setup'!A20&"" | B53: =IF(N('Amazon Path (AGL)'!F38)=0,"",'Amazon Path (AGL)'!H38) | C53: =IF(N('Scenario 1'!F38)=0,"",'Scenario 1'!H38) | D53: =IF(N('Scenario 2'!F38)=0,"",'Scenario 2'!H38) | E53: =IF(N('Scenario 3'!F38)=0,"",'Scenario 3'!H38)
A54: ='Shipment Setup'!A21&"" | B54: =IF(N('Amazon Path (AGL)'!F39)=0,"",'Amazon Path (AGL)'!H39) | C54: =IF(N('Scenario 1'!F39)=0,"",'Scenario 1'!H39) | D54: =IF(N('Scenario 2'!F39)=0,"",'Scenario 2'!H39) | E54: =IF(N('Scenario 3'!F39)=0,"",'Scenario 3'!H39)
A55: ='Shipment Setup'!A22&"" | B55: =IF(N('Amazon Path (AGL)'!F40)=0,"",'Amazon Path (AGL)'!H40) | C55: =IF(N('Scenario 1'!F40)=0,"",'Scenario 1'!H40) | D55: =IF(N('Scenario 2'!F40)=0,"",'Scenario 2'!H40) | E55: =IF(N('Scenario 3'!F40)=0,"",'Scenario 3'!H40)
A56: ='Shipment Setup'!A23&"" | B56: =IF(N('Amazon Path (AGL)'!F41)=0,"",'Amazon Path (AGL)'!H41) | C56: =IF(N('Scenario 1'!F41)=0,"",'Scenario 1'!H41) | D56: =IF(N('Scenario 2'!F41)=0,"",'Scenario 2'!H41) | E56: =IF(N('Scenario 3'!F41)=0,"",'Scenario 3'!H41)

Sheet Products
A1: PRODUCT MASTER
A2: One row per product. Yellow = input. Carton, COGS and duty data are blank until confirmed - the shipment tabs read from here.
A4: Product | B4: SKU / ASIN | C4: Units per carton | D4: Carton L (cm) | E4: Carton W (cm) | F4: Carton H (cm) | G4: Carton gross kg | H4: CBM per carton | I4: Unit COGS ($, customs value) | J4: HTS code | K4: Base duty % | L4: Tariff % (301 etc.) | M4: Other tax % | N4: AWD inbound + processing $/unit | O4: AWD to FBA transfer $/unit | P4: Notes
A5: Classic Food Mill | H5: =IF(AND(N(D5)>0,N(E5)>0,N(F5)>0),D5*E5*F5/1000000,0) -> 0 | N5: 0.23 | O5: 0.4 | P5: Unit 15.2 x 4.01 x 9.6 in, 2.75 lb
A6: Premium Food Mill | H6: =IF(AND(N(D6)>0,N(E6)>0,N(F6)>0),D6*E6*F6/1000000,0) -> 0 | N6: 0.23 | O6: 0.4
A7: Compact Food Mill | H7: =IF(AND(N(D7)>0,N(E7)>0,N(F7)>0),D7*E7*F7/1000000,0) -> 0 | N7: 0.17 | O7: 0.25
A8: Canning Kit | H8: =IF(AND(N(D8)>0,N(E8)>0,N(F8)>0),D8*E8*F8/1000000,0) -> 0 | N8: 0.11 | O8: 0.16
H9: =IF(AND(N(D9)>0,N(E9)>0,N(F9)>0),D9*E9*F9/1000000,0) -> 0
H10: =IF(AND(N(D10)>0,N(E10)>0,N(F10)>0),D10*E10*F10/1000000,0) -> 0
H11: =IF(AND(N(D11)>0,N(E11)>0,N(F11)>0),D11*E11*F11/1000000,0) -> 0
H12: =IF(AND(N(D12)>0,N(E12)>0,N(F12)>0),D12*E12*F12/1000000,0) -> 0
H13: =IF(AND(N(D13)>0,N(E13)>0,N(F13)>0),D13*E13*F13/1000000,0) -> 0
H14: =IF(AND(N(D14)>0,N(E14)>0,N(F14)>0),D14*E14*F14/1000000,0) -> 0
H15: =IF(AND(N(D15)>0,N(E15)>0,N(F15)>0),D15*E15*F15/1000000,0) -> 0
H16: =IF(AND(N(D16)>0,N(E16)>0,N(F16)>0),D16*E16*F16/1000000,0) -> 0
H17: =IF(AND(N(D17)>0,N(E17)>0,N(F17)>0),D17*E17*F17/1000000,0) -> 0
H18: =IF(AND(N(D18)>0,N(E18)>0,N(F18)>0),D18*E18*F18/1000000,0) -> 0
H19: =IF(AND(N(D19)>0,N(E19)>0,N(F19)>0),D19*E19*F19/1000000,0) -> 0
H20: =IF(AND(N(D20)>0,N(E20)>0,N(F20)>0),D20*E20*F20/1000000,0) -> 0
... H34: =IF(AND(N(D34)>0,N(E34)>0,N(F34)>0),D34*E34*F34/1000000,0) -> 0
A36: AWD fee seeds are the Sept 2026 figures from the 2027 Logistics Strategy doc - VERIFY, rates change.

Sheet Rate Card
A1: RATE CARD (reference rates, not quotes)
A2: Freight and tariff costs come from the quote inputs on each scenario. This tab holds only Amazon fee references. Every rate needs a source and a verified date.
A4: Rate | B4: Value | C4: Source / how to verify | D4: Date verified | E4: Status
A5: Inbound placement fee, $/unit (FBA direct, avg) | B5: 0.5 | C5: Seller Central > Reports > Payments; range $0.27-$1.58/unit. Seed is the doc example. | E5: =IF(D5="","VERIFY",IF(TODAY()-D5>60,"STALE","OK")) -> VERIFY
A6: AWD storage, $/CBM/month | C6: Seller Central > AWD fee schedule | E6: =IF(D6="","VERIFY",IF(TODAY()-D6>60,"STALE","OK")) -> VERIFY
A7: Air volumetric factor, kg per CBM | B7: 167 | C7: Standard 6000 cm3/kg = 167 kg/CBM; confirm with carrier | E7: =IF(D7="","VERIFY",IF(TODAY()-D7>60,"STALE","OK")) -> VERIFY
A8: AGL discount vs market (reference, %) | C8: Victoria Step 1, Q2. Informational only. | E8: =IF(D8="","VERIFY",IF(TODAY()-D8>60,"STALE","OK")) -> VERIFY
A9: AWD UK vs SSD Logistix (reference) | C9: Victoria Step 1, Q7 | E9: =IF(D9="","VERIFY",IF(TODAY()-D9>60,"STALE","OK")) -> VERIFY
A11: AWD / channel inbound rules (notes)
A12: Placement fee waived when inventory goes through AWD (confirm in Step 1, Q1).
A13: AGL discount applies only to Amazon-bound volume; ask AGL for the minimum volume and mixed-load rules.
A14: WFS and FBT direct inbound requirements: Step 1, Q4 and Q5.

Sheet Shipment Log
A1: SHIPMENT LOG
A2: After deciding, copy Comparison totals (Comparison B28:E28) and paste values here so the history survives the next shipment.
A4: Date | B4: Shipment / PO | C4: Products | D4: Units | E4: Amazon total | F4: Scenario 1 total | G4: Scenario 2 total | H4: Scenario 3 total | I4: Chosen path | J4: Chosen total | K4: Saving vs Amazon | L4: Reason / notes
J5: =IF(I5="","",INDEX(E5:H5,MATCH(I5,{"Amazon","Scenario 1","Scenario 2","Scenario 3"},0))) | K5: =IF(OR(J5="",E5=""),"",E5-J5)
J6: =IF(I6="","",INDEX(E6:H6,MATCH(I6,{"Amazon","Scenario 1","Scenario 2","Scenario 3"},0))) | K6: =IF(OR(J6="",E6=""),"",E6-J6)
J7: =IF(I7="","",INDEX(E7:H7,MATCH(I7,{"Amazon","Scenario 1","Scenario 2","Scenario 3"},0))) | K7: =IF(OR(J7="",E7=""),"",E7-J7)
J8: =IF(I8="","",INDEX(E8:H8,MATCH(I8,{"Amazon","Scenario 1","Scenario 2","Scenario 3"},0))) | K8: =IF(OR(J8="",E8=""),"",E8-J8)
J9: =IF(I9="","",INDEX(E9:H9,MATCH(I9,{"Amazon","Scenario 1","Scenario 2","Scenario 3"},0))) | K9: =IF(OR(J9="",E9=""),"",E9-J9)
J10: =IF(I10="","",INDEX(E10:H10,MATCH(I10,{"Amazon","Scenario 1","Scenario 2","Scenario 3"},0))) | K10: =IF(OR(J10="",E10=""),"",E10-J10)
J11: =IF(I11="","",INDEX(E11:H11,MATCH(I11,{"Amazon","Scenario 1","Scenario 2","Scenario 3"},0))) | K11: =IF(OR(J11="",E11=""),"",E11-J11)
J12: =IF(I12="","",INDEX(E12:H12,MATCH(I12,{"Amazon","Scenario 1","Scenario 2","Scenario 3"},0))) | K12: =IF(OR(J12="",E12=""),"",E12-J12)
J13: =IF(I13="","",INDEX(E13:H13,MATCH(I13,{"Amazon","Scenario 1","Scenario 2","Scenario 3"},0))) | K13: =IF(OR(J13="",E13=""),"",E13-J13)
J14: =IF(I14="","",INDEX(E14:H14,MATCH(I14,{"Amazon","Scenario 1","Scenario 2","Scenario 3"},0))) | K14: =IF(OR(J14="",E14=""),"",E14-J14)
J15: =IF(I15="","",INDEX(E15:H15,MATCH(I15,{"Amazon","Scenario 1","Scenario 2","Scenario 3"},0))) | K15: =IF(OR(J15="",E15=""),"",E15-J15)
J16: =IF(I16="","",INDEX(E16:H16,MATCH(I16,{"Amazon","Scenario 1","Scenario 2","Scenario 3"},0))) | K16: =IF(OR(J16="",E16=""),"",E16-J16)
... J54: =IF(I54="","",INDEX(E54:H54,MATCH(I54,{"Amazon","Scenario 1","Scenario 2","Scenario 3"},0))) | K54: =IF(OR(J54="",E54=""),"",E54-J54)

Sheet Checks
A1: CHECKS
A2: Fix anything marked CHECK, EXPIRED or VERIFY before relying on the Comparison.
A4: Check | B4: Status | C4: What to do
A5: Products and units entered | B5: =IF('Shipment Setup'!B24>0,"OK","CHECK") -> OK | C5: Shipment Setup: pick products, enter units
A6: Every unit is assigned to a destination | B6: =IF(AND('Shipment Setup'!B24>0,SUMPRODUCT(ABS('Shipment Setup'!T14:T23))=0),"OK","CHECK") -> OK | C6: Shipment Setup: Unallocated units must be 0
A7: Carton CBM and kg known for all products | B7: =IF(SUMPRODUCT(('Shipment Setup'!B14:B23>0)*(('Shipment Setup'!E14:E23=0)+('Shipment Setup'!G14:G23=0)))=0,"OK","CHECK") -> CHECK | C7: Products tab: carton size and kg
A8: Unit COGS known for all products (needed for duty) | B8: =IF(SUMPRODUCT(('Shipment Setup'!B14:B23>0)*('Shipment Setup'!I14:I23=0))=0,"OK","CHECK") -> CHECK | C8: Products tab: unit COGS
A9: Rate Card verified within 60 days | B9: =IF(COUNTIF('Rate Card'!E5:E7,"OK")=3,"OK","VERIFY") -> VERIFY | C9: Rate Card: update the date verified
A10: Amazon Path (AGL): quote entered | B10: =IF('Amazon Path (AGL)'!F16=0,"CHECK","OK") -> CHECK | C10: Enter the quote on that tab
A11: Amazon Path (AGL): quote still valid at shipment date | B11: =IF('Amazon Path (AGL)'!F16=0,"n/a",IF('Amazon Path (AGL)'!B6="","CHECK",IF('Amazon Path (AGL)'!B6>='Shipment Setup'!B6,"OK","EXPIRED"))) -> n/a | C11: Enter valid-until date or refresh the quote
A12: Amazon Path (AGL): totals reconcile (by destination and product) | B12: =IF('Amazon Path (AGL)'!F16=0,"n/a",IF(AND(ABS(SUM('Amazon Path (AGL)'!G25:G28)-'Amazon Path (AGL)'!F16)<0.01,ABS(SUM('Amazon Path (AGL)'!G32:G41)-'Amazon Path (AGL)'!F16)<0.01),"OK","CHECK")) -> n/a | C12: A cost is assigned to a destination with no units
A13: Scenario 1: quote entered | B13: =IF('Scenario 1'!F16=0,"n/a","OK") -> n/a | C13: Enter the quote on that tab
A14: Scenario 1: Incoterm and mode selected | B14: =IF('Scenario 1'!F16=0,"n/a",IF(AND('Scenario 1'!B8<>"",'Scenario 1'!B9<>""),"OK","CHECK")) -> n/a | C14: Pick Incoterm and mode
A15: Scenario 1: quote still valid at shipment date | B15: =IF('Scenario 1'!F16=0,"n/a",IF('Scenario 1'!B7="","CHECK",IF('Scenario 1'!B7>='Shipment Setup'!B6,"OK","EXPIRED"))) -> n/a | C15: Enter valid-until date or refresh the quote
A16: Scenario 1: totals reconcile (by destination and product) | B16: =IF('Scenario 1'!F16=0,"n/a",IF(AND(ABS(SUM('Scenario 1'!G25:G28)-'Scenario 1'!F16)<0.01,ABS(SUM('Scenario 1'!G32:G41)-'Scenario 1'!F16)<0.01),"OK","CHECK")) -> n/a | C16: A cost is assigned to a destination with no units
A17: Scenario 2: quote entered | B17: =IF('Scenario 2'!F16=0,"n/a","OK") -> n/a | C17: Enter the quote on that tab
A18: Scenario 2: Incoterm and mode selected | B18: =IF('Scenario 2'!F16=0,"n/a",IF(AND('Scenario 2'!B8<>"",'Scenario 2'!B9<>""),"OK","CHECK")) -> n/a | C18: Pick Incoterm and mode
A19: Scenario 2: quote still valid at shipment date | B19: =IF('Scenario 2'!F16=0,"n/a",IF('Scenario 2'!B7="","CHECK",IF('Scenario 2'!B7>='Shipment Setup'!B6,"OK","EXPIRED"))) -> n/a | C19: Enter valid-until date or refresh the quote
A20: Scenario 2: totals reconcile (by destination and product) | B20: =IF('Scenario 2'!F16=0,"n/a",IF(AND(ABS(SUM('Scenario 2'!G25:G28)-'Scenario 2'!F16)<0.01,ABS(SUM('Scenario 2'!G32:G41)-'Scenario 2'!F16)<0.01),"OK","CHECK")) -> n/a | C20: A cost is assigned to a destination with no units
A21: Scenario 3: quote entered | B21: =IF('Scenario 3'!F16=0,"n/a","OK") -> n/a | C21: Enter the quote on that tab
A22: Scenario 3: Incoterm and mode selected | B22: =IF('Scenario 3'!F16=0,"n/a",IF(AND('Scenario 3'!B8<>"",'Scenario 3'!B9<>""),"OK","CHECK")) -> n/a | C22: Pick Incoterm and mode
A23: Scenario 3: quote still valid at shipment date | B23: =IF('Scenario 3'!F16=0,"n/a",IF('Scenario 3'!B7="","CHECK",IF('Scenario 3'!B7>='Shipment Setup'!B6,"OK","EXPIRED"))) -> n/a | C23: Enter valid-until date or refresh the quote
A24: Scenario 3: totals reconcile (by destination and product) | B24: =IF('Scenario 3'!F16=0,"n/a",IF(AND(ABS(SUM('Scenario 3'!G25:G28)-'Scenario 3'!F16)<0.01,ABS(SUM('Scenario 3'!G32:G41)-'Scenario 3'!F16)<0.01),"OK","CHECK")) -> n/a | C24: A cost is assigned to a destination with no units
